{
  "name": "t_02-06-11_231",
  "lang": "en",
  "tokens": [
    {
      "index": "39984",
      "text": "We",
      "lemma": "we",
      "pos": "PRP",
      "morph": "_",
      "mother": "39985",
      "rel": "SBJ"
    },
    {
      "index": "39985",
      "text": "are",
      "lemma": "be",
      "pos": "VBP",
      "morph": "_",
      "mother": "39983",
      "rel": "ROOT"
    },
    {
      "index": "39986",
      "text": "very",
      "lemma": "very",
      "pos": "RB",
      "morph": "_",
      "mother": "39987",
      "rel": "AMOD"
    },
    {
      "index": "39987",
      "text": "grateful",
      "lemma": "grateful",
      "pos": "JJ",
      "morph": "_",
      "mother": "39985",
      "rel": "PRD"
    },
    {
      "index": "39988",
      "text": "to",
      "lemma": "to",
      "pos": "TO",
      "morph": "_",
      "mother": "39987",
      "rel": "AMOD"
    },
    {
      "index": "39989",
      "text": "Mr",
      "lemma": "mr",
      "pos": "NNP",
      "morph": "_",
      "mother": "39990",
      "rel": "TITLE"
    },
    {
      "index": "39990",
      "text": "Perry",
      "lemma": "perry",
      "pos": "NNP",
      "morph": "_",
      "mother": "39988",
      "rel": "PMOD"
    },
    {
      "index": "39991",
      "text": "for",
      "lemma": "for",
      "pos": "IN",
      "morph": "_",
      "mother": "39987",
      "rel": "AMOD"
    },
    {
      "index": "39992",
      "text": "this",
      "lemma": "this",
      "pos": "DT",
      "morph": "_",
      "mother": "39993",
      "rel": "NMOD"
    },
    {
      "index": "39993",
      "text": "question",
      "lemma": "question",
      "pos": "NN",
      "morph": "_",
      "mother": "39991",
      "rel": "PMOD"
    },
    {
      "index": "39994",
      "text": "because",
      "lemma": "because",
      "pos": "IN",
      "morph": "_",
      "mother": "39985",
      "rel": "PRP"
    },
    {
      "index": "39995",
      "text": "Parliament",
      "lemma": "parliament",
      "pos": "NNP",
      "morph": "_",
      "mother": "39996",
      "rel": "SBJ"
    },
    {
      "index": "39996",
      "text": "has",
      "lemma": "have",
      "pos": "VBZ",
      "morph": "_",
      "mother": "39994",
      "rel": "SUB"
    },
    {
      "index": "39997",
      "text": "in",
      "lemma": "in",
      "pos": "IN",
      "morph": "_",
      "mother": "39996",
      "rel": "VC"
    },
    {
      "index": "39998",
      "text": "numerous",
      "lemma": "numerous",
      "pos": "JJ",
      "morph": "_",
      "mother": "39999",
      "rel": "NMOD"
    },
    {
      "index": "39999",
      "text": "reports",
      "lemma": "report",
      "pos": "NNS",
      "morph": "_",
      "mother": "39997",
      "rel": "PMOD"
    },
    {
      "index": "40000",
      "text": "asked",
      "lemma": "ask",
      "pos": "VBN",
      "morph": "_",
      "mother": "39999",
      "rel": "APPO"
    },
    {
      "index": "40001",
      "text": "for",
      "lemma": "for",
      "pos": "IN",
      "morph": "_",
      "mother": "40000",
      "rel": "ADV"
    },
    {
      "index": "40002",
      "text": "a",
      "lemma": "a",
      "pos": "DT",
      "morph": "_",
      "mother": "40003",
      "rel": "NMOD"
    },
    {
      "index": "40003",
      "text": "revision",
      "lemma": "revision",
      "pos": "NN",
      "morph": "_",
      "mother": "40001",
      "rel": "PMOD"
    },
    {
      "index": "40004",
      "text": "and",
      "lemma": "and",
      "pos": "CC",
      "morph": "_",
      "mother": "40001",
      "rel": "COORD"
    },
    {
      "index": "40005",
      "text": "for",
      "lemma": "for",
      "pos": "IN",
      "morph": "_",
      "mother": "40004",
      "rel": "CONJ"
    },
    {
      "index": "40006",
      "text": "the",
      "lemma": "the",
      "pos": "DT",
      "morph": "_",
      "mother": "40007",
      "rel": "NMOD"
    },
    {
      "index": "40007",
      "text": "Commission",
      "lemma": "commission",
      "pos": "NNP",
      "morph": "_",
      "mother": "40008",
      "rel": "SBJ"
    },
    {
      "index": "40008",
      "text": "to",
      "lemma": "to",
      "pos": "TO",
      "morph": "_",
      "mother": "40005",
      "rel": "SUB"
    },
    {
      "index": "40009",
      "text": "do",
      "lemma": "do",
      "pos": "VB",
      "morph": "_",
      "mother": "40008",
      "rel": "IM"
    },
    {
      "index": "40010",
      "text": "something",
      "lemma": "something",
      "pos": "NN",
      "morph": "_",
      "mother": "40009",
      "rel": "OBJ"
    },
    {
      "index": "40011",
      "text": "about",
      "lemma": "about",
      "pos": "IN",
      "morph": "_",
      "mother": "40009",
      "rel": "ADV"
    },
    {
      "index": "40012",
      "text": "this",
      "lemma": "this",
      "pos": "DT",
      "morph": "_",
      "mother": "40011",
      "rel": "PMOD"
    },
    {
      "index": "40013",
      "text": ".",
      "lemma": ".",
      "pos": ".",
      "morph": "_",
      "mother": "39985",
      "rel": "P"
    },
    {
      "index": "40014",
      "text": "We",
      "lemma": "we",
      "pos": "PRP",
      "morph": "_",
      "mother": "40015",
      "rel": "SBJ"
    },
    {
      "index": "40015",
      "text": "had",
      "lemma": "have",
      "pos": "VBD",
      "morph": "_",
      "mother": "40013",
      "rel": "ROOT"
    },
    {
      "index": "40016",
      "text": "a",
      "lemma": "a",
      "pos": "DT",
      "morph": "_",
      "mother": "40017",
      "rel": "NMOD"
    },
    {
      "index": "40017",
      "text": "report",
      "lemma": "report",
      "pos": "NN",
      "morph": "_",
      "mother": "40015",
      "rel": "OBJ"
    },
    {
      "index": "40018",
      "text": "on",
      "lemma": "on",
      "pos": "IN",
      "morph": "_",
      "mother": "40017",
      "rel": "NMOD"
    },
    {
      "index": "40019",
      "text": "digital",
      "lemma": "digital",
      "pos": "JJ",
      "morph": "_",
      "mother": "40020",
      "rel": "NMOD"
    },
    {
      "index": "40020",
      "text": "television",
      "lemma": "television",
      "pos": "NN",
      "morph": "_",
      "mother": "40018",
      "rel": "PMOD"
    },
    {
      "index": "40021",
      "text": "where",
      "lemma": "where",
      "pos": "WRB",
      "morph": "_",
      "mother": "40026",
      "rel": "LOC"
    },
    {
      "index": "40022",
      "text": "this",
      "lemma": "this",
      "pos": "DT",
      "morph": "_",
      "mother": "40024",
      "rel": "NMOD"
    },
    {
      "index": "40023",
      "text": "same",
      "lemma": "same",
      "pos": "JJ",
      "morph": "_",
      "mother": "40024",
      "rel": "NMOD"
    },
    {
      "index": "40024",
      "text": "issue",
      "lemma": "issue",
      "pos": "NN",
      "morph": "_",
      "mother": "40025",
      "rel": "SBJ"
    },
    {
      "index": "40025",
      "text": "was",
      "lemma": "be",
      "pos": "VBD",
      "morph": "_",
      "mother": "40017",
      "rel": "NMOD"
    },
    {
      "index": "40026",
      "text": "raised",
      "lemma": "raise",
      "pos": "VBN",
      "morph": "_",
      "mother": "40025",
      "rel": "VC"
    },
    {
      "index": "40027",
      "text": ".",
      "lemma": ".",
      "pos": ".",
      "morph": "_",
      "mother": "40015",
      "rel": "P"
    },
    {
      "index": "40028",
      "text": "I",
      "lemma": "i",
      "pos": "PRP",
      "morph": "_",
      "mother": "40029",
      "rel": "SBJ"
    },
    {
      "index": "40029",
      "text": "cannot",
      "lemma": "cannot",
      "pos": "VBP",
      "morph": "_",
      "mother": "40030",
      "rel": "SBJ"
    },
    {
      "index": "40030",
      "text": "say",
      "lemma": "say",
      "pos": "VBP",
      "morph": "_",
      "mother": "40027",
      "rel": "ROOT"
    },
    {
      "index": "40031",
      "text": "whose",
      "lemma": "whose",
      "pos": "WP$",
      "morph": "_",
      "mother": "40032",
      "rel": "NMOD"
    },
    {
      "index": "40032",
      "text": "name",
      "lemma": "name",
      "pos": "NN",
      "morph": "_",
      "mother": "40030",
      "rel": "OBJ"
    },
    {
      "index": "40033",
      "text": "this",
      "lemma": "this",
      "pos": "DT",
      "morph": "_",
      "mother": "40034",
      "rel": "NMOD"
    },
    {
      "index": "40034",
      "text": "report",
      "lemma": "report",
      "pos": "NN",
      "morph": "_",
      "mother": "40035",
      "rel": "SBJ"
    },
    {
      "index": "40035",
      "text": "bore",
      "lemma": "bore",
      "pos": "VBD",
      "morph": "_",
      "mother": "40032",
      "rel": "NMOD"
    },
    {
      "index": "40036",
      "text": ",",
      "lemma": ",",
      "pos": ",",
      "morph": "_",
      "mother": "40030",
      "rel": "P"
    },
    {
      "index": "40037",
      "text": "I",
      "lemma": "i",
      "pos": "PRP",
      "morph": "_",
      "mother": "40038",
      "rel": "SBJ"
    },
    {
      "index": "40038",
      "text": "am",
      "lemma": "be",
      "pos": "VBP",
      "morph": "_",
      "mother": "40030",
      "rel": "OBJ"
    },
    {
      "index": "40039",
      "text": "too",
      "lemma": "too",
      "pos": "RB",
      "morph": "_",
      "mother": "40038",
      "rel": "ADV"
    },
    {
      "index": "40040",
      "text": "humble",
      "lemma": "humble",
      "pos": "VB",
      "morph": "_",
      "mother": "40038",
      "rel": "VC"
    },
    {
      "index": "40041",
      "text": "for",
      "lemma": "for",
      "pos": "IN",
      "morph": "_",
      "mother": "40040",
      "rel": "ADV"
    },
    {
      "index": "40042",
      "text": "that",
      "lemma": "that",
      "pos": "DT",
      "morph": "_",
      "mother": "40041",
      "rel": "PMOD"
    },
    {
      "index": "40043",
      "text": ".",
      "lemma": ".",
      "pos": ".",
      "morph": "_",
      "mother": "40030",
      "rel": "P"
    },
    {
      "index": "40044",
      "text": "So",
      "lemma": "so",
      "pos": "RB",
      "morph": "_",
      "mother": "40047",
      "rel": "ADV"
    },
    {
      "index": "40045",
      "text": ",",
      "lemma": ",",
      "pos": ",",
      "morph": "_",
      "mother": "40047",
      "rel": "P"
    },
    {
      "index": "40046",
      "text": "there",
      "lemma": "there",
      "pos": "EX",
      "morph": "_",
      "mother": "40047",
      "rel": "SBJ"
    },
    {
      "index": "40047",
      "text": "were",
      "lemma": "be",
      "pos": "VBD",
      "morph": "_",
      "mother": "40043",
      "rel": "ROOT"
    },
    {
      "index": "40048",
      "text": "a",
      "lemma": "a",
      "pos": "DT",
      "morph": "_",
      "mother": "40049",
      "rel": "NMOD"
    },
    {
      "index": "40049",
      "text": "number",
      "lemma": "number",
      "pos": "NN",
      "morph": "_",
      "mother": "40047",
      "rel": "PRD"
    },
    {
      "index": "40050",
      "text": "of",
      "lemma": "of",
      "pos": "IN",
      "morph": "_",
      "mother": "40049",
      "rel": "NMOD"
    },
    {
      "index": "40051",
      "text": "reports",
      "lemma": "report",
      "pos": "NNS",
      "morph": "_",
      "mother": "40050",
      "rel": "PMOD"
    },
    {
      "index": "40052",
      "text": "where",
      "lemma": "where",
      "pos": "WRB",
      "morph": "_",
      "mother": "40054",
      "rel": "LOC"
    },
    {
      "index": "40053",
      "text": "we",
      "lemma": "we",
      "pos": "PRP",
      "morph": "_",
      "mother": "40054",
      "rel": "SBJ"
    },
    {
      "index": "40054",
      "text": "asked",
      "lemma": "ask",
      "pos": "VBD",
      "morph": "_",
      "mother": "40049",
      "rel": "NMOD"
    },
    {
      "index": "40055",
      "text": "for",
      "lemma": "for",
      "pos": "IN",
      "morph": "_",
      "mother": "40054",
      "rel": "ADV"
    },
    {
      "index": "40056",
      "text": "that",
      "lemma": "that",
      "pos": "DT",
      "morph": "_",
      "mother": "40055",
      "rel": "PMOD"
    },
    {
      "index": "40057",
      "text": "as",
      "lemma": "as",
      "pos": "IN",
      "morph": "_",
      "mother": "40058",
      "rel": "AMOD"
    },
    {
      "index": "40058",
      "text": "well",
      "lemma": "well",
      "pos": "RB",
      "morph": "_",
      "mother": "40047",
      "rel": "ADV"
    },
    {
      "index": "40059",
      "text": ".",
      "lemma": ".",
      "pos": ".",
      "morph": "_",
      "mother": "40047",
      "rel": "P"
    },
    {
      "index": "40060",
      "text": "It",
      "lemma": "it",
      "pos": "PRP",
      "morph": "_",
      "mother": "40061",
      "rel": "SBJ"
    },
    {
      "index": "40061",
      "text": "is",
      "lemma": "be",
      "pos": "VBZ",
      "morph": "_",
      "mother": "40059",
      "rel": "ROOT"
    },
    {
      "index": "40062",
      "text": "ironic",
      "lemma": "ironic",
      "pos": "JJ",
      "morph": "_",
      "mother": "40061",
      "rel": "PRD"
    },
    {
      "index": "40063",
      "text": "that",
      "lemma": "that",
      "pos": "IN",
      "morph": "_",
      "mother": "40061",
      "rel": "EXTR"
    },
    {
      "index": "40064",
      "text": "we",
      "lemma": "we",
      "pos": "PRP",
      "morph": "_",
      "mother": "40065",
      "rel": "SBJ"
    },
    {
      "index": "40065",
      "text": "have",
      "lemma": "have",
      "pos": "VBP",
      "morph": "_",
      "mother": "40063",
      "rel": "SUB"
    },
    {
      "index": "40066",
      "text": "a",
      "lemma": "a",
      "pos": "DT",
      "morph": "_",
      "mother": "40067",
      "rel": "NMOD"
    },
    {
      "index": "40067",
      "text": "directive",
      "lemma": "directive",
      "pos": "NN",
      "morph": "_",
      "mother": "40065",
      "rel": "OBJ"
    },
    {
      "index": "40068",
      "text": "called",
      "lemma": "call",
      "pos": "VBN",
      "morph": "_",
      "mother": "40067",
      "rel": "APPO"
    },
    {
      "index": "40069",
      "text": "television",
      "lemma": "television",
      "pos": "NN",
      "morph": "_",
      "mother": "40068",
      "rel": "OPRD"
    },
    {
      "index": "40070",
      "text": "without",
      "lemma": "without",
      "pos": "IN",
      "morph": "_",
      "mother": "40068",
      "rel": "ADV"
    },
    {
      "index": "40071",
      "text": "frontiers",
      "lemma": "frontier",
      "pos": "NNS",
      "morph": "_",
      "mother": "40070",
      "rel": "PMOD"
    },
    {
      "index": "40072",
      "text": "while",
      "lemma": "while",
      "pos": "IN",
      "morph": "_",
      "mother": "40068",
      "rel": "ADV"
    },
    {
      "index": "40073",
      "text": "the",
      "lemma": "the",
      "pos": "DT",
      "morph": "_",
      "mother": "40074",
      "rel": "NMOD"
    },
    {
      "index": "40074",
      "text": "copyright",
      "lemma": "copyright",
      "pos": "NN",
      "morph": "_",
      "mother": "40081",
      "rel": "SBJ"
    },
    {
      "index": "40075",
      "text": "and",
      "lemma": "and",
      "pos": "CC",
      "morph": "_",
      "mother": "40074",
      "rel": "COORD"
    },
    {
      "index": "40076",
      "text": "the",
      "lemma": "the",
      "pos": "DT",
      "morph": "_",
      "mother": "40077",
      "rel": "NMOD"
    },
    {
      "index": "40077",
      "text": "rules",
      "lemma": "rule",
      "pos": "NNS",
      "morph": "_",
      "mother": "40075",
      "rel": "CONJ"
    },
    {
      "index": "40078",
      "text": "on",
      "lemma": "on",
      "pos": "IN",
      "morph": "_",
      "mother": "40077",
      "rel": "NMOD"
    },
    {
      "index": "40079",
      "text": "collection",
      "lemma": "collection",
      "pos": "NN",
      "morph": "_",
      "mother": "40080",
      "rel": "NMOD"
    },
    {
      "index": "40080",
      "text": "societies",
      "lemma": "society",
      "pos": "NNS",
      "morph": "_",
      "mother": "40078",
      "rel": "PMOD"
    },
    {
      "index": "40081",
      "text": "are",
      "lemma": "be",
      "pos": "VBP",
      "morph": "_",
      "mother": "40072",
      "rel": "SUB"
    },
    {
      "index": "40082",
      "text": "preventing",
      "lemma": "prevent",
      "pos": "VBG",
      "morph": "_",
      "mother": "40081",
      "rel": "VC"
    },
    {
      "index": "40083",
      "text": "us",
      "lemma": "us",
      "pos": "PRP",
      "morph": "_",
      "mother": "40082",
      "rel": "OBJ"
    },
    {
      "index": "40084",
      "text": "from",
      "lemma": "from",
      "pos": "IN",
      "morph": "_",
      "mother": "40082",
      "rel": "ADV"
    },
    {
      "index": "40085",
      "text": "doing",
      "lemma": "do",
      "pos": "VBG",
      "morph": "_",
      "mother": "40084",
      "rel": "PMOD"
    },
    {
      "index": "40086",
      "text": "anything",
      "lemma": "anything",
      "pos": "NN",
      "morph": "_",
      "mother": "40085",
      "rel": "OBJ"
    },
    {
      "index": "40087",
      "text": ".",
      "lemma": ".",
      "pos": ".",
      "morph": "_",
      "mother": "40061",
      "rel": "P"
    },
    {
      "index": "40088",
      "text": "I",
      "lemma": "i",
      "pos": "PRP",
      "morph": "_",
      "mother": "40089",
      "rel": "SBJ"
    },
    {
      "index": "40089",
      "text": "would",
      "lemma": "would",
      "pos": "MD",
      "morph": "_",
      "mother": "40087",
      "rel": "ROOT"
    },
    {
      "index": "40090",
      "text": "ask",
      "lemma": "ask",
      "pos": "VB",
      "morph": "_",
      "mother": "40089",
      "rel": "VC"
    },
    {
      "index": "40091",
      "text": "the",
      "lemma": "the",
      "pos": "DT",
      "morph": "_",
      "mother": "40092",
      "rel": "NMOD"
    },
    {
      "index": "40092",
      "text": "Commissioner",
      "lemma": "commissioner",
      "pos": "NN",
      "morph": "_",
      "mother": "40090",
      "rel": "OBJ"
    },
    {
      "index": "40093",
      "text": "about",
      "lemma": "about",
      "pos": "IN",
      "morph": "_",
      "mother": "40090",
      "rel": "ADV"
    },
    {
      "index": "40094",
      "text": "this",
      "lemma": "this",
      "pos": "DT",
      "morph": "_",
      "mother": "40095",
      "rel": "NMOD"
    },
    {
      "index": "40095",
      "text": "review",
      "lemma": "review",
      "pos": "NN",
      "morph": "_",
      "mother": "40093",
      "rel": "PMOD"
    },
    {
      "index": "40096",
      "text": "and",
      "lemma": "and",
      "pos": "CC",
      "morph": "_",
      "mother": "40095",
      "rel": "COORD"
    },
    {
      "index": "40097",
      "text": "the",
      "lemma": "the",
      "pos": "DT",
      "morph": "_",
      "mother": "40098",
      "rel": "NMOD"
    },
    {
      "index": "40098",
      "text": "study",
      "lemma": "study",
      "pos": "NN",
      "morph": "_",
      "mother": "40096",
      "rel": "CONJ"
    },
    {
      "index": "40099",
      "text": "that",
      "lemma": "that",
      "pos": "IN",
      "morph": "_",
      "mother": "40098",
      "rel": "NMOD"
    },
    {
      "index": "40100",
      "text": "he",
      "lemma": "he",
      "pos": "PRP",
      "morph": "_",
      "mother": "40101",
      "rel": "SBJ"
    },
    {
      "index": "40101",
      "text": "is",
      "lemma": "be",
      "pos": "VBZ",
      "morph": "_",
      "mother": "40099",
      "rel": "SUB"
    },
    {
      "index": "40102",
      "text": "going",
      "lemma": "go",
      "pos": "VBG",
      "morph": "_",
      "mother": "40101",
      "rel": "VC"
    },
    {
      "index": "40103",
      "text": "to",
      "lemma": "to",
      "pos": "TO",
      "morph": "_",
      "mother": "40102",
      "rel": "VC"
    },
    {
      "index": "40104",
      "text": "undertake",
      "lemma": "undertake",
      "pos": "VB",
      "morph": "_",
      "mother": "40103",
      "rel": "IM"
    },
    {
      "index": "40105",
      "text": ":",
      "lemma": ":",
      "pos": ":",
      "morph": "_",
      "mother": "40090",
      "rel": "P"
    },
    {
      "index": "40106",
      "text": "are",
      "lemma": "be",
      "pos": "VBP",
      "morph": "_",
      "mother": "40090",
      "rel": "COORD"
    },
    {
      "index": "40107",
      "text": "you",
      "lemma": "you",
      "pos": "PRP",
      "morph": "_",
      "mother": "40106",
      "rel": "SBJ"
    },
    {
      "index": "40108",
      "text": "also",
      "lemma": "also",
      "pos": "RB",
      "morph": "_",
      "mother": "40106",
      "rel": "ADV"
    },
    {
      "index": "40109",
      "text": "going",
      "lemma": "go",
      "pos": "VBG",
      "morph": "_",
      "mother": "40106",
      "rel": "VC"
    },
    {
      "index": "40110",
      "text": "to",
      "lemma": "to",
      "pos": "TO",
      "morph": "_",
      "mother": "40109",
      "rel": "VC"
    },
    {
      "index": "40111",
      "text": "look",
      "lemma": "look",
      "pos": "VB",
      "morph": "_",
      "mother": "40110",
      "rel": "IM"
    },
    {
      "index": "40112",
      "text": "at",
      "lemma": "at",
      "pos": "IN",
      "morph": "_",
      "mother": "40111",
      "rel": "ADV"
    },
    {
      "index": "40113",
      "text": "the",
      "lemma": "the",
      "pos": "DT",
      "morph": "_",
      "mother": "40114",
      "rel": "NMOD"
    },
    {
      "index": "40114",
      "text": "differences",
      "lemma": "difference",
      "pos": "NNS",
      "morph": "_",
      "mother": "40112",
      "rel": "PMOD"
    },
    {
      "index": "40115",
      "text": "in",
      "lemma": "in",
      "pos": "IN",
      "morph": "_",
      "mother": "40114",
      "rel": "LOC"
    },
    {
      "index": "40116",
      "text": "operation",
      "lemma": "operation",
      "pos": "NN",
      "morph": "_",
      "mother": "40115",
      "rel": "PMOD"
    },
    {
      "index": "40117",
      "text": "between",
      "lemma": "between",
      "pos": "IN",
      "morph": "_",
      "mother": "40114",
      "rel": "NMOD"
    },
    {
      "index": "40118",
      "text": "cable",
      "lemma": "cable",
      "pos": "NN",
      "morph": "_",
      "mother": "40117",
      "rel": "PMOD"
    },
    {
      "index": "40119",
      "text": "and",
      "lemma": "and",
      "pos": "CC",
      "morph": "_",
      "mother": "40118",
      "rel": "COORD"
    },
    {
      "index": "40120",
      "text": "satellite",
      "lemma": "satellite",
      "pos": "NN",
      "morph": "_",
      "mother": "40119",
      "rel": "CONJ"
    },
    {
      "index": "40121",
      "text": "that",
      "lemma": "that",
      "pos": "WDT",
      "morph": "_",
      "mother": "40123",
      "rel": "SBJ"
    },
    {
      "index": "40122",
      "text": "also",
      "lemma": "also",
      "pos": "RB",
      "morph": "_",
      "mother": "40123",
      "rel": "ADV"
    },
    {
      "index": "40123",
      "text": "exist",
      "lemma": "exist",
      "pos": "VBP",
      "morph": "_",
      "mother": "40114",
      "rel": "NMOD"
    },
    {
      "index": "40124",
      "text": "in",
      "lemma": "in",
      "pos": "IN",
      "morph": "_",
      "mother": "40123",
      "rel": "LOC"
    },
    {
      "index": "40125",
      "text": "the",
      "lemma": "the",
      "pos": "DT",
      "morph": "_",
      "mother": "40126",
      "rel": "NMOD"
    },
    {
      "index": "40126",
      "text": "directive",
      "lemma": "directive",
      "pos": "NN",
      "morph": "_",
      "mother": "40124",
      "rel": "PMOD"
    },
    {
      "index": "40127",
      "text": "and",
      "lemma": "and",
      "pos": "CC",
      "morph": "_",
      "mother": "40106",
      "rel": "COORD"
    },
    {
      "index": "40128",
      "text": "are",
      "lemma": "be",
      "pos": "VBP",
      "morph": "_",
      "mother": "40127",
      "rel": "CONJ"
    },
    {
      "index": "40129",
      "text": "also",
      "lemma": "also",
      "pos": "RB",
      "morph": "_",
      "mother": "40128",
      "rel": "ADV"
    },
    {
      "index": "40130",
      "text": "unsatisfactory",
      "lemma": "unsatisfactory",
      "pos": "JJ",
      "morph": "_",
      "mother": "40128",
      "rel": "PRD"
    },
    {
      "index": "40131",
      "text": "?",
      "lemma": "?",
      "pos": ".",
      "morph": "_",
      "mother": "40089",
      "rel": "P"
    },
    {
      "index": "40132",
      "text": "In",
      "lemma": "in",
      "pos": "IN",
      "morph": "_",
      "mother": "40155",
      "rel": "LOC"
    },
    {
      "index": "40133",
      "text": "your",
      "lemma": "your",
      "pos": "PRP$",
      "morph": "_",
      "mother": "40134",
      "rel": "NMOD"
    },
    {
      "index": "40134",
      "text": "report",
      "lemma": "report",
      "pos": "NN",
      "morph": "_",
      "mother": "40132",
      "rel": "PMOD"
    },
    {
      "index": "40135",
      "text": "will",
      "lemma": "will",
      "pos": "MD",
      "morph": "_",
      "mother": "40131",
      "rel": "ROOT"
    },
    {
      "index": "40136",
      "text": "you",
      "lemma": "you",
      "pos": "PRP",
      "morph": "_",
      "mother": "40135",
      "rel": "SBJ"
    },
    {
      "index": "40137",
      "text": "look",
      "lemma": "look",
      "pos": "VB",
      "morph": "_",
      "mother": "40135",
      "rel": "VC"
    },
    {
      "index": "40138",
      "text": "at",
      "lemma": "at",
      "pos": "IN",
      "morph": "_",
      "mother": "40137",
      "rel": "ADV"
    },
    {
      "index": "40139",
      "text": "the",
      "lemma": "the",
      "pos": "DT",
      "morph": "_",
      "mother": "40140",
      "rel": "NMOD"
    },
    {
      "index": "40140",
      "text": "role",
      "lemma": "role",
      "pos": "NN",
      "morph": "_",
      "mother": "40138",
      "rel": "PMOD"
    },
    {
      "index": "40141",
      "text": "the",
      "lemma": "the",
      "pos": "DT",
      "morph": "_",
      "mother": "40143",
      "rel": "NMOD"
    },
    {
      "index": "40142",
      "text": "collecting",
      "lemma": "collect",
      "pos": "VBG",
      "morph": "_",
      "mother": "40143",
      "rel": "NMOD"
    },
    {
      "index": "40143",
      "text": "societies",
      "lemma": "society",
      "pos": "NNS",
      "morph": "_",
      "mother": "40148",
      "rel": "SBJ"
    },
    {
      "index": "40144",
      "text": "for",
      "lemma": "for",
      "pos": "IN",
      "morph": "_",
      "mother": "40143",
      "rel": "NMOD"
    },
    {
      "index": "40145",
      "text": "the",
      "lemma": "the",
      "pos": "DT",
      "morph": "_",
      "mother": "40147",
      "rel": "NMOD"
    },
    {
      "index": "40146",
      "text": "copyright",
      "lemma": "copyright",
      "pos": "NN",
      "morph": "_",
      "mother": "40147",
      "rel": "NMOD"
    },
    {
      "index": "40147",
      "text": "owners",
      "lemma": "owner",
      "pos": "NNS",
      "morph": "_",
      "mother": "40144",
      "rel": "PMOD"
    },
    {
      "index": "40148",
      "text": "are",
      "lemma": "be",
      "pos": "VBP",
      "morph": "_",
      "mother": "40140",
      "rel": "NMOD"
    },
    {
      "index": "40149",
      "text": "playing",
      "lemma": "play",
      "pos": "VBG",
      "morph": "_",
      "mother": "40148",
      "rel": "VC"
    },
    {
      "index": "40150",
      "text": "in",
      "lemma": "in",
      "pos": "IN",
      "morph": "_",
      "mother": "40149",
      "rel": "LOC"
    },
    {
      "index": "40151",
      "text": "this",
      "lemma": "this",
      "pos": "DT",
      "morph": "_",
      "mother": "40152",
      "rel": "NMOD"
    },
    {
      "index": "40152",
      "text": "field",
      "lemma": "field",
      "pos": "NN",
      "morph": "_",
      "mother": "40150",
      "rel": "PMOD"
    },
    {
      "index": "40153",
      "text": "which",
      "lemma": "which",
      "pos": "WDT",
      "morph": "_",
      "mother": "40155",
      "rel": "SBJ"
    },
    {
      "index": "40154",
      "text": "also",
      "lemma": "also",
      "pos": "RB",
      "morph": "_",
      "mother": "40155",
      "rel": "ADV"
    },
    {
      "index": "40155",
      "text": "prevents",
      "lemma": "prevent",
      "pos": "VBZ",
      "morph": "_",
      "mother": "40152",
      "rel": "NMOD"
    },
    {
      "index": "40156",
      "text": "the",
      "lemma": "the",
      "pos": "DT",
      "morph": "_",
      "mother": "40157",
      "rel": "NMOD"
    },
    {
      "index": "40157",
      "text": "functioning",
      "lemma": "functioning",
      "pos": "NN",
      "morph": "_",
      "mother": "40155",
      "rel": "OBJ"
    },
    {
      "index": "40158",
      "text": "of",
      "lemma": "of",
      "pos": "IN",
      "morph": "_",
      "mother": "40157",
      "rel": "NMOD"
    },
    {
      "index": "40159",
      "text": "the",
      "lemma": "the",
      "pos": "DT",
      "morph": "_",
      "mother": "40161",
      "rel": "NMOD"
    },
    {
      "index": "40160",
      "text": "internal",
      "lemma": "internal",
      "pos": "JJ",
      "morph": "_",
      "mother": "40161",
      "rel": "NMOD"
    },
    {
      "index": "40161",
      "text": "market",
      "lemma": "market",
      "pos": "NN",
      "morph": "_",
      "mother": "40158",
      "rel": "PMOD"
    },
    {
      "index": "40162",
      "text": "?",
      "lemma": "?",
      "pos": ".",
      "morph": "_",
      "mother": "40135",
      "rel": "P"
    }
  ],
  "sentences": [
    [
      0,
      30
    ],
    [
      30,
      44
    ],
    [
      44,
      60
    ],
    [
      60,
      76
    ],
    [
      76,
      104
    ],
    [
      104,
      148
    ],
    [
      148,
      179
    ]
  ],
  "anaphors": [
    {
      "id": "markable_3367",
      "shellnoun": "true",
      "align_unit": "set_365",
      "content": "external",
      "start": 9,
      "end": 10,
      "index": 0
    }
  ],
  "antecedents": [
    {
      "id": "markable_3370",
      "nominal": "false",
      "align_unit": "set_367",
      "start": 122,
      "end": 148,
      "index": 0
    },
    {
      "id": "markable_3371",
      "nominal": "false",
      "align_unit": "set_366",
      "start": 148,
      "end": 179,
      "index": 1
    }
  ],
  "ref_instances": []
}