{
  "name": "t_06-09-25_21",
  "lang": "de",
  "tokens": [
    {
      "index": "46641",
      "text": "Herr",
      "lemma": "Herr",
      "pos": "NN",
      "morph": "nom|sg|masc",
      "mother": "46640",
      "rel": "--"
    },
    {
      "index": "46642",
      "text": "Pr\u00e4sident",
      "lemma": "Pr\u00e4sident",
      "pos": "NN",
      "morph": "nom|sg|masc",
      "mother": "46641",
      "rel": "NK"
    },
    {
      "index": "46643",
      "text": "!",
      "lemma": "--",
      "pos": "$.",
      "morph": "_",
      "mother": "46642",
      "rel": "--"
    },
    {
      "index": "46644",
      "text": "Vergangene",
      "lemma": "vergangen",
      "pos": "ADJA",
      "morph": "acc|sg|fem|pos",
      "mother": "46645",
      "rel": "NK"
    },
    {
      "index": "46645",
      "text": "Woche",
      "lemma": "Woche",
      "pos": "NN",
      "morph": "acc|sg|fem",
      "mother": "46646",
      "rel": "MO"
    },
    {
      "index": "46646",
      "text": "gelangte",
      "lemma": "gelangen",
      "pos": "VVFIN",
      "morph": "sg|3|past|ind",
      "mother": "46643",
      "rel": "--"
    },
    {
      "index": "46647",
      "text": "ein",
      "lemma": "ein",
      "pos": "ART",
      "morph": "nom|sg|neut",
      "mother": "46648",
      "rel": "NK"
    },
    {
      "index": "46648",
      "text": "Tonbandmitschnitt",
      "lemma": "Tonbandmitschnitt",
      "pos": "NN",
      "morph": "nom|sg|neut",
      "mother": "46646",
      "rel": "SB"
    },
    {
      "index": "46649",
      "text": "an",
      "lemma": "an",
      "pos": "APPR",
      "morph": "_",
      "mother": "46646",
      "rel": "MO"
    },
    {
      "index": "46650",
      "text": "die",
      "lemma": "der",
      "pos": "ART",
      "morph": "acc|sg|fem",
      "mother": "46651",
      "rel": "NK"
    },
    {
      "index": "46651",
      "text": "\u00d6ffentlichkeit",
      "lemma": "\u00d6ffentlichkeit",
      "pos": "NN",
      "morph": "acc|sg|fem",
      "mother": "46649",
      "rel": "NK"
    },
    {
      "index": "46652",
      "text": ",",
      "lemma": "--",
      "pos": "$,",
      "morph": "_",
      "mother": "46651",
      "rel": "--"
    },
    {
      "index": "46653",
      "text": "auf",
      "lemma": "auf",
      "pos": "APPR",
      "morph": "_",
      "mother": "46660",
      "rel": "MO"
    },
    {
      "index": "46654",
      "text": "dem",
      "lemma": "der",
      "pos": "PRELS",
      "morph": "dat|sg|masc",
      "mother": "46653",
      "rel": "NK"
    },
    {
      "index": "46655",
      "text": "sich",
      "lemma": "sich",
      "pos": "PRF",
      "morph": "acc|sg|3",
      "mother": "46660",
      "rel": "OA"
    },
    {
      "index": "46656",
      "text": "der",
      "lemma": "der",
      "pos": "ART",
      "morph": "nom|sg|masc",
      "mother": "46658",
      "rel": "NK"
    },
    {
      "index": "46657",
      "text": "ungarische",
      "lemma": "ungarisch",
      "pos": "ADJA",
      "morph": "nom|sg|masc|pos",
      "mother": "46658",
      "rel": "NK"
    },
    {
      "index": "46658",
      "text": "Ministerpr\u00e4sident",
      "lemma": "Ministerpr\u00e4sident",
      "pos": "NN",
      "morph": "nom|sg|masc",
      "mother": "46660",
      "rel": "SB"
    },
    {
      "index": "46659",
      "text": "folgenderma\u00dfen",
      "lemma": "folgenderma\u00dfen",
      "pos": "ADV",
      "morph": "_",
      "mother": "46660",
      "rel": "MO"
    },
    {
      "index": "46660",
      "text": "\u00e4u\u00dferte",
      "lemma": "\u00e4u\u00dfern",
      "pos": "VVFIN",
      "morph": "sg|3|past|ind",
      "mother": "46651",
      "rel": "RC"
    },
    {
      "index": "46661",
      "text": ":",
      "lemma": "--",
      "pos": "$.",
      "morph": "_",
      "mother": "46660",
      "rel": "--"
    },
    {
      "index": "46662",
      "text": "\"",
      "lemma": "--",
      "pos": "$(",
      "morph": "_",
      "mother": "46663",
      "rel": "--"
    },
    {
      "index": "46663",
      "text": "Wir",
      "lemma": "wir",
      "pos": "PPER",
      "morph": "nom|pl|*|1",
      "mother": "46664",
      "rel": "SB"
    },
    {
      "index": "46664",
      "text": "haben",
      "lemma": "haben",
      "pos": "VAFIN",
      "morph": "pl|1|pres|ind",
      "mother": "46661",
      "rel": "--"
    },
    {
      "index": "46665",
      "text": "die",
      "lemma": "der",
      "pos": "ART",
      "morph": "acc|pl|masc",
      "mother": "46666",
      "rel": "NK"
    },
    {
      "index": "46666",
      "text": "Menschen",
      "lemma": "Mensch",
      "pos": "NN",
      "morph": "acc|pl|masc",
      "mother": "46683",
      "rel": "OA"
    },
    {
      "index": "46667",
      "text": "18",
      "lemma": "18",
      "pos": "CARD",
      "morph": "_",
      "mother": "46668",
      "rel": "NK"
    },
    {
      "index": "46668",
      "text": "Monate",
      "lemma": "Monat",
      "pos": "NN",
      "morph": "acc|pl|masc",
      "mother": "46669",
      "rel": "AMS"
    },
    {
      "index": "46669",
      "text": "lang",
      "lemma": "lang",
      "pos": "ADJD",
      "morph": "pos",
      "mother": "46683",
      "rel": "MO"
    },
    {
      "index": "46670",
      "text": "--",
      "lemma": "-",
      "pos": "TRUNC",
      "morph": "_",
      "mother": "46671",
      "rel": "CJ"
    },
    {
      "index": "46671",
      "text": "vormittags",
      "lemma": "vormittags",
      "pos": "ADV",
      "morph": "_",
      "mother": "46683",
      "rel": "MO"
    },
    {
      "index": "46672",
      "text": ",",
      "lemma": "--",
      "pos": "$,",
      "morph": "_",
      "mother": "46671",
      "rel": "--"
    },
    {
      "index": "46673",
      "text": "nachmittags",
      "lemma": "nachmittags",
      "pos": "ADV",
      "morph": "_",
      "mother": "46683",
      "rel": "MO"
    },
    {
      "index": "46674",
      "text": "und",
      "lemma": "und",
      "pos": "KON",
      "morph": "_",
      "mother": "46673",
      "rel": "CD"
    },
    {
      "index": "46675",
      "text": "abends",
      "lemma": "abends",
      "pos": "ADV",
      "morph": "_",
      "mother": "46683",
      "rel": "MO"
    },
    {
      "index": "46676",
      "text": "--",
      "lemma": "-",
      "pos": "TRUNC",
      "morph": "_",
      "mother": "46674",
      "rel": "CJ"
    },
    {
      "index": "46677",
      "text": "\u00fcber",
      "lemma": "\u00fcber",
      "pos": "APPR",
      "morph": "_",
      "mother": "46683",
      "rel": "OP"
    },
    {
      "index": "46678",
      "text": "die",
      "lemma": "der",
      "pos": "ART",
      "morph": "acc|sg|fem",
      "mother": "46680",
      "rel": "NK"
    },
    {
      "index": "46679",
      "text": "wirtschaftliche",
      "lemma": "wirtschaftlich",
      "pos": "ADJA",
      "morph": "acc|sg|fem|pos",
      "mother": "46680",
      "rel": "NK"
    },
    {
      "index": "46680",
      "text": "Lage",
      "lemma": "Lage",
      "pos": "NN",
      "morph": "acc|sg|fem",
      "mother": "46677",
      "rel": "NK"
    },
    {
      "index": "46681",
      "text": "unseres",
      "lemma": "unser",
      "pos": "PPOSAT",
      "morph": "gen|sg|neut",
      "mother": "46682",
      "rel": "NK"
    },
    {
      "index": "46682",
      "text": "Landes",
      "lemma": "Land",
      "pos": "NN",
      "morph": "gen|sg|neut",
      "mother": "46680",
      "rel": "AG"
    },
    {
      "index": "46683",
      "text": "belogen",
      "lemma": "bel\u00fcgen",
      "pos": "VVPP",
      "morph": "_",
      "mother": "46664",
      "rel": "OC"
    },
    {
      "index": "46684",
      "text": ".",
      "lemma": "--",
      "pos": "$.",
      "morph": "_",
      "mother": "46683",
      "rel": "--"
    },
    {
      "index": "46685",
      "text": "Und",
      "lemma": "und",
      "pos": "KON",
      "morph": "_",
      "mother": "46687",
      "rel": "JU"
    },
    {
      "index": "46686",
      "text": "wir",
      "lemma": "wir",
      "pos": "PPER",
      "morph": "nom|pl|*|1",
      "mother": "46687",
      "rel": "SB"
    },
    {
      "index": "46687",
      "text": "haben",
      "lemma": "haben",
      "pos": "VAFIN",
      "morph": "pl|1|pres|ind",
      "mother": "46684",
      "rel": "--"
    },
    {
      "index": "46688",
      "text": "gelogen",
      "lemma": "gelogen",
      "pos": "VVPP",
      "morph": "_",
      "mother": "46687",
      "rel": "OC"
    },
    {
      "index": "46689",
      "text": ",",
      "lemma": "--",
      "pos": "$,",
      "morph": "_",
      "mother": "46688",
      "rel": "--"
    },
    {
      "index": "46690",
      "text": "um",
      "lemma": "um",
      "pos": "KOUI",
      "morph": "_",
      "mother": "46694",
      "rel": "CP"
    },
    {
      "index": "46691",
      "text": "die",
      "lemma": "der",
      "pos": "ART",
      "morph": "acc|pl|fem",
      "mother": "46692",
      "rel": "NK"
    },
    {
      "index": "46692",
      "text": "Wahlen",
      "lemma": "Wahl",
      "pos": "NN",
      "morph": "acc|pl|fem",
      "mother": "46694",
      "rel": "OA"
    },
    {
      "index": "46693",
      "text": "zu",
      "lemma": "zu",
      "pos": "PTKZU",
      "morph": "_",
      "mother": "46694",
      "rel": "PM"
    },
    {
      "index": "46694",
      "text": "gewinnen",
      "lemma": "gewinnen",
      "pos": "VVINF",
      "morph": "_",
      "mother": "46688",
      "rel": "MO"
    },
    {
      "index": "46695",
      "text": ".",
      "lemma": "--",
      "pos": "$.",
      "morph": "_",
      "mother": "46694",
      "rel": "--"
    },
    {
      "index": "46696",
      "text": "\"",
      "lemma": "--",
      "pos": "$(",
      "morph": "_",
      "mother": "46695",
      "rel": "--"
    },
    {
      "index": "46697",
      "text": "Daraufhin",
      "lemma": "daraufhin",
      "pos": "PROAV",
      "morph": "_",
      "mother": "46698",
      "rel": "MO"
    },
    {
      "index": "46698",
      "text": "gingen",
      "lemma": "gehen",
      "pos": "VVFIN",
      "morph": "pl|3|past|ind",
      "mother": "46696",
      "rel": "--"
    },
    {
      "index": "46699",
      "text": "Hunderttausende",
      "lemma": "Hunderttausend",
      "pos": "NN",
      "morph": "nom|pl|neut",
      "mother": "46698",
      "rel": "SB"
    },
    {
      "index": "46700",
      "text": "Menschen",
      "lemma": "Mensch",
      "pos": "NN",
      "morph": "nom|pl|masc",
      "mother": "46699",
      "rel": "NK"
    },
    {
      "index": "46701",
      "text": "in",
      "lemma": "in",
      "pos": "APPR",
      "morph": "_",
      "mother": "46698",
      "rel": "MO"
    },
    {
      "index": "46702",
      "text": "ganz",
      "lemma": "ganz",
      "pos": "ADV",
      "morph": "pos",
      "mother": "46703",
      "rel": "NK"
    },
    {
      "index": "46703",
      "text": "Ungarn",
      "lemma": "Ungarn",
      "pos": "NN",
      "morph": "nom|pl|masc",
      "mother": "46701",
      "rel": "NK"
    },
    {
      "index": "46704",
      "text": "auf",
      "lemma": "auf",
      "pos": "APPR",
      "morph": "_",
      "mother": "46698",
      "rel": "MO"
    },
    {
      "index": "46705",
      "text": "die",
      "lemma": "der",
      "pos": "ART",
      "morph": "acc|sg|fem",
      "mother": "46706",
      "rel": "NK"
    },
    {
      "index": "46706",
      "text": "Stra\u00dfe",
      "lemma": "Stra\u00dfe",
      "pos": "NN",
      "morph": "acc|sg|fem",
      "mother": "46704",
      "rel": "NK"
    },
    {
      "index": "46707",
      "text": "und",
      "lemma": "und",
      "pos": "KON",
      "morph": "_",
      "mother": "46698",
      "rel": "CD"
    },
    {
      "index": "46708",
      "text": "forderten",
      "lemma": "fordern",
      "pos": "VVFIN",
      "morph": "pl|3|past|ind",
      "mother": "46707",
      "rel": "CJ"
    },
    {
      "index": "46709",
      "text": "seinen",
      "lemma": "sein",
      "pos": "PPOSAT",
      "morph": "acc|sg|masc",
      "mother": "46710",
      "rel": "NK"
    },
    {
      "index": "46710",
      "text": "R\u00fccktritt",
      "lemma": "R\u00fccktritt",
      "pos": "NN",
      "morph": "acc|sg|masc",
      "mother": "46708",
      "rel": "OA"
    },
    {
      "index": "46711",
      "text": ".",
      "lemma": "--",
      "pos": "$.",
      "morph": "_",
      "mother": "46710",
      "rel": "--"
    },
    {
      "index": "46712",
      "text": "Auch",
      "lemma": "auch",
      "pos": "ADV",
      "morph": "_",
      "mother": "46714",
      "rel": "MO"
    },
    {
      "index": "46713",
      "text": "die",
      "lemma": "der",
      "pos": "ART",
      "morph": "nom|sg|fem",
      "mother": "46714",
      "rel": "NK"
    },
    {
      "index": "46714",
      "text": "PPE-DE-Fraktion",
      "lemma": "PPE-DE-Fraktion",
      "pos": "NN",
      "morph": "nom|sg|fem",
      "mother": "46715",
      "rel": "SB"
    },
    {
      "index": "46715",
      "text": "forderte",
      "lemma": "fordern",
      "pos": "VVFIN",
      "morph": "sg|3|past|ind",
      "mother": "46711",
      "rel": "--"
    },
    {
      "index": "46716",
      "text": "den",
      "lemma": "der",
      "pos": "ART",
      "morph": "acc|sg|masc",
      "mother": "46717",
      "rel": "NK"
    },
    {
      "index": "46717",
      "text": "Regierungschef",
      "lemma": "Regierungschef",
      "pos": "NN",
      "morph": "acc|sg|masc",
      "mother": "46715",
      "rel": "OA"
    },
    {
      "index": "46718",
      "text": "auf",
      "lemma": "auf",
      "pos": "PTKVZ",
      "morph": "_",
      "mother": "46715",
      "rel": "SVP"
    },
    {
      "index": "46719",
      "text": ",",
      "lemma": "--",
      "pos": "$,",
      "morph": "_",
      "mother": "46718",
      "rel": "--"
    },
    {
      "index": "46720",
      "text": "von",
      "lemma": "von",
      "pos": "APPR",
      "morph": "_",
      "mother": "46723",
      "rel": "OP"
    },
    {
      "index": "46721",
      "text": "seinem",
      "lemma": "sein",
      "pos": "PPOSAT",
      "morph": "dat|sg|neut",
      "mother": "46722",
      "rel": "NK"
    },
    {
      "index": "46722",
      "text": "Amt",
      "lemma": "Amt",
      "pos": "NN",
      "morph": "dat|sg|neut",
      "mother": "46720",
      "rel": "NK"
    },
    {
      "index": "46723",
      "text": "zur\u00fcckzutreten",
      "lemma": "zur\u00fccktreten",
      "pos": "VVINF",
      "morph": "_",
      "mother": "46715",
      "rel": "OC"
    },
    {
      "index": "46724",
      "text": ".",
      "lemma": "--",
      "pos": "$.",
      "morph": "_",
      "mother": "46723",
      "rel": "--"
    },
    {
      "index": "46725",
      "text": "Doch",
      "lemma": "doch",
      "pos": "KON",
      "morph": "_",
      "mother": "46731",
      "rel": "JU"
    },
    {
      "index": "46726",
      "text": "die",
      "lemma": "der",
      "pos": "ART",
      "morph": "nom|pl|fem",
      "mother": "46728",
      "rel": "NK"
    },
    {
      "index": "46727",
      "text": "europ\u00e4ischen",
      "lemma": "europ\u00e4isch",
      "pos": "ADJA",
      "morph": "nom|pl|fem|pos",
      "mother": "46728",
      "rel": "NK"
    },
    {
      "index": "46728",
      "text": "Sozialdemokraten",
      "lemma": "Sozialdemokrat",
      "pos": "NN",
      "morph": "nom|pl|fem",
      "mother": "46731",
      "rel": "SB"
    },
    {
      "index": "46729",
      "text": "und",
      "lemma": "und",
      "pos": "KON",
      "morph": "_",
      "mother": "46728",
      "rel": "CD"
    },
    {
      "index": "46730",
      "text": "Liberalen",
      "lemma": "liberale",
      "pos": "NN",
      "morph": "nom|pl|*",
      "mother": "46729",
      "rel": "CJ"
    },
    {
      "index": "46731",
      "text": "gaben",
      "lemma": "geben",
      "pos": "VVFIN",
      "morph": "pl|3|past|ind",
      "mother": "46724",
      "rel": "--"
    },
    {
      "index": "46732",
      "text": "ihrem",
      "lemma": "ihr",
      "pos": "PPOSAT",
      "morph": "dat|sg|masc",
      "mother": "46736",
      "rel": "NK"
    },
    {
      "index": "46733",
      "text": "in",
      "lemma": "in",
      "pos": "APPR",
      "morph": "_",
      "mother": "46735",
      "rel": "CVC"
    },
    {
      "index": "46734",
      "text": "Misskredit",
      "lemma": "Misskredit",
      "pos": "NN",
      "morph": "dat|sg|masc",
      "mother": "46733",
      "rel": "NK"
    },
    {
      "index": "46735",
      "text": "geratenen",
      "lemma": "geraten",
      "pos": "ADJA",
      "morph": "dat|sg|masc|pos",
      "mother": "46736",
      "rel": "NK"
    },
    {
      "index": "46736",
      "text": "Freund",
      "lemma": "Freund",
      "pos": "NN",
      "morph": "dat|sg|masc",
      "mother": "46731",
      "rel": "DA"
    },
    {
      "index": "46737",
      "text": "R\u00fcckendeckung",
      "lemma": "R\u00fcckendeckung",
      "pos": "NN",
      "morph": "nom|sg|fem",
      "mother": "46731",
      "rel": "OA"
    },
    {
      "index": "46738",
      "text": ".",
      "lemma": "--",
      "pos": "$.",
      "morph": "_",
      "mother": "46737",
      "rel": "--"
    },
    {
      "index": "46739",
      "text": "Werte",
      "lemma": "Wert",
      "pos": "ADJA",
      "morph": "acc|pl|fem|pos",
      "mother": "46740",
      "rel": "NK"
    },
    {
      "index": "46740",
      "text": "Kolleginnen",
      "lemma": "Kollegin",
      "pos": "NN",
      "morph": "acc|pl|fem",
      "mother": "46744",
      "rel": "RE"
    },
    {
      "index": "46741",
      "text": "und",
      "lemma": "und",
      "pos": "KON",
      "morph": "_",
      "mother": "46740",
      "rel": "CD"
    },
    {
      "index": "46742",
      "text": "Kollegen",
      "lemma": "Kollege",
      "pos": "NN",
      "morph": "acc|pl|masc",
      "mother": "46741",
      "rel": "CJ"
    },
    {
      "index": "46743",
      "text": ",",
      "lemma": "--",
      "pos": "$,",
      "morph": "_",
      "mother": "46742",
      "rel": "--"
    },
    {
      "index": "46744",
      "text": "das",
      "lemma": "der",
      "pos": "PDS",
      "morph": "nom|sg|neut",
      "mother": "46745",
      "rel": "SB"
    },
    {
      "index": "46745",
      "text": "war",
      "lemma": "sein",
      "pos": "VAFIN",
      "morph": "sg|3|past|ind",
      "mother": "46738",
      "rel": "--"
    },
    {
      "index": "46746",
      "text": "wirklich",
      "lemma": "wirklich",
      "pos": "ADJD",
      "morph": "pos",
      "mother": "46745",
      "rel": "MO"
    },
    {
      "index": "46747",
      "text": "eine",
      "lemma": "ein",
      "pos": "ART",
      "morph": "nom|sg|fem",
      "mother": "46748",
      "rel": "NK"
    },
    {
      "index": "46748",
      "text": "Schande",
      "lemma": "Schande",
      "pos": "NN",
      "morph": "nom|sg|fem",
      "mother": "46745",
      "rel": "PD"
    },
    {
      "index": "46749",
      "text": "!",
      "lemma": "--",
      "pos": "$.",
      "morph": "_",
      "mother": "46748",
      "rel": "--"
    },
    {
      "index": "46750",
      "text": "Zum",
      "lemma": "zu",
      "pos": "APPRART",
      "morph": "dat|sg|masc",
      "mother": "46752",
      "rel": "MO"
    },
    {
      "index": "46751",
      "text": "Gl\u00fcck",
      "lemma": "Gl\u00fcck",
      "pos": "NN",
      "morph": "dat|sg|masc",
      "mother": "46750",
      "rel": "NK"
    },
    {
      "index": "46752",
      "text": "vertraten",
      "lemma": "vertraten",
      "pos": "VVFIN",
      "morph": "pl|3|past|ind",
      "mother": "46749",
      "rel": "--"
    },
    {
      "index": "46753",
      "text": "einige",
      "lemma": "einiger",
      "pos": "PIAT",
      "morph": "nom|pl|masc",
      "mother": "46754",
      "rel": "NK"
    },
    {
      "index": "46754",
      "text": "Sozialisten",
      "lemma": "Sozialist",
      "pos": "NN",
      "morph": "nom|pl|masc",
      "mother": "46752",
      "rel": "SB"
    },
    {
      "index": "46755",
      "text": ",",
      "lemma": "--",
      "pos": "$,",
      "morph": "_",
      "mother": "46754",
      "rel": "--"
    },
    {
      "index": "46756",
      "text": "darunter",
      "lemma": "darunter",
      "pos": "PROAV",
      "morph": "_",
      "mother": "46758",
      "rel": "MO"
    },
    {
      "index": "46757",
      "text": "S\u00e9gol\u00e8ne",
      "lemma": "S\u00e9gol\u00e8ne",
      "pos": "NE",
      "morph": "*|*|*",
      "mother": "46758",
      "rel": "PNC"
    },
    {
      "index": "46758",
      "text": "Royal",
      "lemma": "Royal",
      "pos": "NE",
      "morph": "*|*|*",
      "mother": "46754",
      "rel": "PAR"
    },
    {
      "index": "46759",
      "text": ",",
      "lemma": "--",
      "pos": "$,",
      "morph": "_",
      "mother": "46758",
      "rel": "--"
    },
    {
      "index": "46760",
      "text": "einen",
      "lemma": "ein",
      "pos": "ART",
      "morph": "acc|sg|masc",
      "mother": "46762",
      "rel": "NK"
    },
    {
      "index": "46761",
      "text": "gegens\u00e4tzlichen",
      "lemma": "gegens\u00e4tzlich",
      "pos": "ADJA",
      "morph": "acc|sg|masc|pos",
      "mother": "46762",
      "rel": "NK"
    },
    {
      "index": "46762",
      "text": "Standpunkt",
      "lemma": "Standpunkt",
      "pos": "NN",
      "morph": "acc|sg|masc",
      "mother": "46752",
      "rel": "OA"
    },
    {
      "index": "46763",
      "text": "und",
      "lemma": "und",
      "pos": "KON",
      "morph": "_",
      "mother": "46752",
      "rel": "CD"
    },
    {
      "index": "46764",
      "text": "verlangten",
      "lemma": "verlangen",
      "pos": "VVFIN",
      "morph": "pl|3|past|ind",
      "mother": "46763",
      "rel": "CJ"
    },
    {
      "index": "46765",
      "text": "ebenfalls",
      "lemma": "ebenfalls",
      "pos": "ADV",
      "morph": "_",
      "mother": "46764",
      "rel": "MO"
    },
    {
      "index": "46766",
      "text": "den",
      "lemma": "der",
      "pos": "ART",
      "morph": "acc|sg|masc",
      "mother": "46767",
      "rel": "NK"
    },
    {
      "index": "46767",
      "text": "R\u00fccktritt",
      "lemma": "R\u00fccktritt",
      "pos": "NN",
      "morph": "acc|sg|masc",
      "mother": "46764",
      "rel": "OA"
    },
    {
      "index": "46768",
      "text": "des",
      "lemma": "der",
      "pos": "ART",
      "morph": "gen|sg|masc",
      "mother": "46769",
      "rel": "NK"
    },
    {
      "index": "46769",
      "text": "Ministerpr\u00e4sidenten",
      "lemma": "Ministerpr\u00e4sident",
      "pos": "NN",
      "morph": "gen|sg|masc",
      "mother": "46767",
      "rel": "AG"
    },
    {
      "index": "46770",
      "text": ".",
      "lemma": "--",
      "pos": "$.",
      "morph": "_",
      "mother": "46769",
      "rel": "--"
    },
    {
      "index": "46771",
      "text": "Hiermit",
      "lemma": "hiermit",
      "pos": "PROAV",
      "morph": "_",
      "mother": "46772",
      "rel": "MO"
    },
    {
      "index": "46772",
      "text": "rufe",
      "lemma": "rufen",
      "pos": "VVFIN",
      "morph": "sg|1|pres|ind",
      "mother": "46770",
      "rel": "--"
    },
    {
      "index": "46773",
      "text": "ich",
      "lemma": "ich",
      "pos": "PPER",
      "morph": "nom|sg|*|1",
      "mother": "46772",
      "rel": "SB"
    },
    {
      "index": "46774",
      "text": "unsere",
      "lemma": "unser",
      "pos": "PPOSAT",
      "morph": "acc|sg|fem",
      "mother": "46778",
      "rel": "NK"
    },
    {
      "index": "46775",
      "text": "sozialdemokratischen",
      "lemma": "sozialdemokratisch",
      "pos": "ADJA",
      "morph": "gen|sg|fem|pos",
      "mother": "46778",
      "rel": "NK"
    },
    {
      "index": "46776",
      "text": "und",
      "lemma": "und",
      "pos": "KON",
      "morph": "_",
      "mother": "46775",
      "rel": "CD"
    },
    {
      "index": "46777",
      "text": "liberalen",
      "lemma": "liberal",
      "pos": "ADJA",
      "morph": "nom|pl|fem|pos",
      "mother": "46776",
      "rel": "CJ"
    },
    {
      "index": "46778",
      "text": "Kolleginnen",
      "lemma": "Kollegin",
      "pos": "NN",
      "morph": "nom|pl|fem",
      "mother": "46772",
      "rel": "OA"
    },
    {
      "index": "46779",
      "text": "und",
      "lemma": "und",
      "pos": "KON",
      "morph": "_",
      "mother": "46778",
      "rel": "CD"
    },
    {
      "index": "46780",
      "text": "Kollegen",
      "lemma": "Kollege",
      "pos": "NN",
      "morph": "nom|pl|masc",
      "mother": "46779",
      "rel": "CJ"
    },
    {
      "index": "46781",
      "text": "auf",
      "lemma": "auf",
      "pos": "PTKVZ",
      "morph": "_",
      "mother": "46772",
      "rel": "SVP"
    },
    {
      "index": "46782",
      "text": ",",
      "lemma": "--",
      "pos": "$,",
      "morph": "_",
      "mother": "46781",
      "rel": "--"
    },
    {
      "index": "46783",
      "text": "ihre",
      "lemma": "ihr",
      "pos": "PPOSAT",
      "morph": "acc|sg|fem",
      "mother": "46784",
      "rel": "NK"
    },
    {
      "index": "46784",
      "text": "Haltung",
      "lemma": "Haltung",
      "pos": "NN",
      "morph": "acc|sg|fem",
      "mother": "46788",
      "rel": "OA"
    },
    {
      "index": "46785",
      "text": "noch",
      "lemma": "noch",
      "pos": "ADV",
      "morph": "_",
      "mother": "46786",
      "rel": "MO"
    },
    {
      "index": "46786",
      "text": "einmal",
      "lemma": "einmal",
      "pos": "ADV",
      "morph": "_",
      "mother": "46788",
      "rel": "MO"
    },
    {
      "index": "46787",
      "text": "zu",
      "lemma": "zu",
      "pos": "PTKZU",
      "morph": "_",
      "mother": "46788",
      "rel": "PM"
    },
    {
      "index": "46788",
      "text": "\u00fcberdenken",
      "lemma": "\u00fcberdenken",
      "pos": "VVINF",
      "morph": "_",
      "mother": "46772",
      "rel": "OC"
    },
    {
      "index": "46789",
      "text": ".",
      "lemma": "--",
      "pos": "$.",
      "morph": "_",
      "mother": "46788",
      "rel": "--"
    },
    {
      "index": "46790",
      "text": "Schlie\u00dflich",
      "lemma": "schlie\u00dflich",
      "pos": "ADV",
      "morph": "_",
      "mother": "46796",
      "rel": "MO"
    },
    {
      "index": "46791",
      "text": "wurden",
      "lemma": "werden",
      "pos": "VAFIN",
      "morph": "pl|3|past|ind",
      "mother": "46789",
      "rel": "--"
    },
    {
      "index": "46792",
      "text": "die",
      "lemma": "der",
      "pos": "ART",
      "morph": "nom|pl|masc",
      "mother": "46794",
      "rel": "NK"
    },
    {
      "index": "46793",
      "text": "ungarischen",
      "lemma": "ungarisch",
      "pos": "ADJA",
      "morph": "nom|pl|masc|pos",
      "mother": "46794",
      "rel": "NK"
    },
    {
      "index": "46794",
      "text": "B\u00fcrger",
      "lemma": "B\u00fcrger",
      "pos": "NN",
      "morph": "nom|pl|masc",
      "mother": "46791",
      "rel": "SB"
    },
    {
      "index": "46795",
      "text": "systematisch",
      "lemma": "systematisch",
      "pos": "ADJD",
      "morph": "pos",
      "mother": "46796",
      "rel": "MO"
    },
    {
      "index": "46796",
      "text": "belogen",
      "lemma": "beliehen",
      "pos": "VVPP",
      "morph": "_",
      "mother": "46791",
      "rel": "OC"
    },
    {
      "index": "46797",
      "text": ",",
      "lemma": "--",
      "pos": "$,",
      "morph": "_",
      "mother": "46796",
      "rel": "--"
    },
    {
      "index": "46798",
      "text": "und",
      "lemma": "und",
      "pos": "KON",
      "morph": "_",
      "mother": "46791",
      "rel": "CD"
    },
    {
      "index": "46799",
      "text": "das",
      "lemma": "der",
      "pos": "PDS",
      "morph": "nom|sg|neut",
      "mother": "46800",
      "rel": "SB"
    },
    {
      "index": "46800",
      "text": "kann",
      "lemma": "k\u00f6nnen",
      "pos": "VMFIN",
      "morph": "sg|3|pres|ind",
      "mother": "46798",
      "rel": "CJ"
    },
    {
      "index": "46801",
      "text": "ja",
      "lemma": "ja",
      "pos": "ADV",
      "morph": "_",
      "mother": "46800",
      "rel": "MO"
    },
    {
      "index": "46802",
      "text": "wohl",
      "lemma": "wohl",
      "pos": "ADV",
      "morph": "_",
      "mother": "46800",
      "rel": "MO"
    },
    {
      "index": "46803",
      "text": "nicht",
      "lemma": "nicht",
      "pos": "PTKNEG",
      "morph": "_",
      "mother": "46800",
      "rel": "NG"
    },
    {
      "index": "46804",
      "text": "die",
      "lemma": "der",
      "pos": "ART",
      "morph": "acc|sg|fem",
      "mother": "46805",
      "rel": "NK"
    },
    {
      "index": "46805",
      "text": "Art",
      "lemma": "Art",
      "pos": "NN",
      "morph": "acc|sg|fem",
      "mother": "46808",
      "rel": "PD"
    },
    {
      "index": "46806",
      "text": "und",
      "lemma": "und",
      "pos": "KON",
      "morph": "_",
      "mother": "46805",
      "rel": "CD"
    },
    {
      "index": "46807",
      "text": "Weise",
      "lemma": "Weise",
      "pos": "NN",
      "morph": "acc|sg|fem",
      "mother": "46806",
      "rel": "CJ"
    },
    {
      "index": "46808",
      "text": "sein",
      "lemma": "sein",
      "pos": "VAINF",
      "morph": "_",
      "mother": "46800",
      "rel": "OC"
    },
    {
      "index": "46809",
      "text": ",",
      "lemma": "--",
      "pos": "$,",
      "morph": "_",
      "mother": "46808",
      "rel": "--"
    },
    {
      "index": "46810",
      "text": "in",
      "lemma": "in",
      "pos": "APPR",
      "morph": "_",
      "mother": "46817",
      "rel": "MO"
    },
    {
      "index": "46811",
      "text": "der",
      "lemma": "der",
      "pos": "PRELS",
      "morph": "dat|sg|fem",
      "mother": "46810",
      "rel": "NK"
    },
    {
      "index": "46812",
      "text": "wir",
      "lemma": "wir",
      "pos": "PPER",
      "morph": "nom|pl|*|1",
      "mother": "46817",
      "rel": "SB"
    },
    {
      "index": "46813",
      "text": "hier",
      "lemma": "hier",
      "pos": "ADV",
      "morph": "_",
      "mother": "46817",
      "rel": "MO"
    },
    {
      "index": "46814",
      "text": "in",
      "lemma": "in",
      "pos": "APPR",
      "morph": "_",
      "mother": "46817",
      "rel": "MO"
    },
    {
      "index": "46815",
      "text": "Europa",
      "lemma": "Europa",
      "pos": "NE",
      "morph": "dat|sg|neut",
      "mother": "46814",
      "rel": "NK"
    },
    {
      "index": "46816",
      "text": "Politik",
      "lemma": "Politik",
      "pos": "NN",
      "morph": "acc|sg|fem",
      "mother": "46817",
      "rel": "OA"
    },
    {
      "index": "46817",
      "text": "betreiben",
      "lemma": "betreiben",
      "pos": "VVFIN",
      "morph": "_",
      "mother": "46805",
      "rel": "RC"
    },
    {
      "index": "46818",
      "text": ".",
      "lemma": "--",
      "pos": "$.",
      "morph": "_",
      "mother": "46817",
      "rel": "--"
    },
    {
      "index": "46819",
      "text": "Ich",
      "lemma": "ich",
      "pos": "PPER",
      "morph": "nom|sg|*|1",
      "mother": "46820",
      "rel": "SB"
    },
    {
      "index": "46820",
      "text": "hoffe",
      "lemma": "hoffen",
      "pos": "VVFIN",
      "morph": "sg|1|pres|ind",
      "mother": "46818",
      "rel": "--"
    },
    {
      "index": "46821",
      "text": ",",
      "lemma": "--",
      "pos": "$,",
      "morph": "_",
      "mother": "46820",
      "rel": "--"
    },
    {
      "index": "46822",
      "text": "da",
      "lemma": "da",
      "pos": "ADV",
      "morph": "_",
      "mother": "46823",
      "rel": "MO"
    },
    {
      "index": "46823",
      "text": "sind",
      "lemma": "sein",
      "pos": "VAFIN",
      "morph": "pl|1|pres|ind",
      "mother": "46820",
      "rel": "OC"
    },
    {
      "index": "46824",
      "text": "wir",
      "lemma": "wir",
      "pos": "PPER",
      "morph": "nom|pl|*|1",
      "mother": "46823",
      "rel": "SB"
    },
    {
      "index": "46825",
      "text": "uns",
      "lemma": "uns",
      "pos": "PRF",
      "morph": "acc|pl|*|1",
      "mother": "46827",
      "rel": "DA"
    },
    {
      "index": "46826",
      "text": "alle",
      "lemma": "alle",
      "pos": "PIS",
      "morph": "nom|pl|*",
      "mother": "46819",
      "rel": "NK"
    },
    {
      "index": "46827",
      "text": "einig",
      "lemma": "einig",
      "pos": "ADJD",
      "morph": "pos",
      "mother": "46823",
      "rel": "PD"
    },
    {
      "index": "46828",
      "text": ".",
      "lemma": "--",
      "pos": "$.",
      "morph": "_",
      "mother": "46827",
      "rel": "--"
    },
    {
      "index": "46829",
      "text": "Der",
      "lemma": "der",
      "pos": "ART",
      "morph": "nom|sg|masc",
      "mother": "46831",
      "rel": "NK"
    },
    {
      "index": "46830",
      "text": "ver\u00f6ffentlichte",
      "lemma": "ver\u00f6ffentlicht",
      "pos": "ADJA",
      "morph": "nom|sg|masc|pos",
      "mother": "46831",
      "rel": "NK"
    },
    {
      "index": "46831",
      "text": "Tonbandmitschnitt",
      "lemma": "Tonbandmitschnitt",
      "pos": "NN",
      "morph": "nom|sg|masc",
      "mother": "46832",
      "rel": "SB"
    },
    {
      "index": "46832",
      "text": "enthielt",
      "lemma": "enthalten",
      "pos": "VVFIN",
      "morph": "sg|3|past|ind",
      "mother": "46828",
      "rel": "--"
    },
    {
      "index": "46833",
      "text": "auch",
      "lemma": "auch",
      "pos": "ADV",
      "morph": "_",
      "mother": "46835",
      "rel": "MO"
    },
    {
      "index": "46834",
      "text": "eine",
      "lemma": "ein",
      "pos": "ART",
      "morph": "acc|sg|fem",
      "mother": "46835",
      "rel": "NK"
    },
    {
      "index": "46835",
      "text": "Erkl\u00e4rung",
      "lemma": "Erkl\u00e4rung",
      "pos": "NN",
      "morph": "acc|sg|fem",
      "mother": "46832",
      "rel": "OA"
    },
    {
      "index": "46836",
      "text": "des",
      "lemma": "der",
      "pos": "ART",
      "morph": "gen|sg|masc",
      "mother": "46837",
      "rel": "NK"
    },
    {
      "index": "46837",
      "text": "Finanzministers",
      "lemma": "Finanzminister",
      "pos": "NN",
      "morph": "gen|sg|masc",
      "mother": "46835",
      "rel": "AG"
    },
    {
      "index": "46838",
      "text": ",",
      "lemma": "--",
      "pos": "$,",
      "morph": "_",
      "mother": "46837",
      "rel": "--"
    },
    {
      "index": "46839",
      "text": "wonach",
      "lemma": "wonach",
      "pos": "PWAV",
      "morph": "_",
      "mother": "46847",
      "rel": "MO"
    },
    {
      "index": "46840",
      "text": "EU-Kommissar",
      "lemma": "EU-Kommissar",
      "pos": "NN",
      "morph": "nom|sg|masc",
      "mother": "46848",
      "rel": "SB"
    },
    {
      "index": "46841",
      "text": "Alumnia",
      "lemma": "Alumnia",
      "pos": "NE",
      "morph": "nom|sg|masc",
      "mother": "46840",
      "rel": "NK"
    },
    {
      "index": "46842",
      "text": "seinen",
      "lemma": "sein",
      "pos": "PPOSAT",
      "morph": "acc|sg|masc",
      "mother": "46844",
      "rel": "NK"
    },
    {
      "index": "46843",
      "text": "sozialdemokratischen",
      "lemma": "sozialdemokratisch",
      "pos": "ADJA",
      "morph": "acc|sg|masc|pos",
      "mother": "46844",
      "rel": "NK"
    },
    {
      "index": "46844",
      "text": "Kameraden",
      "lemma": "Kamerad",
      "pos": "NN",
      "morph": "acc|sg|masc",
      "mother": "46847",
      "rel": "OA"
    },
    {
      "index": "46845",
      "text": "in",
      "lemma": "in",
      "pos": "APPR",
      "morph": "_",
      "mother": "46844",
      "rel": "MNR"
    },
    {
      "index": "46846",
      "text": "Budapest",
      "lemma": "Budapest",
      "pos": "NE",
      "morph": "dat|sg|neut",
      "mother": "46845",
      "rel": "NK"
    },
    {
      "index": "46847",
      "text": "geholfen",
      "lemma": "helfen",
      "pos": "VVPP",
      "morph": "_",
      "mother": "46848",
      "rel": "OC"
    },
    {
      "index": "46848",
      "text": "habe",
      "lemma": "haben",
      "pos": "VAFIN",
      "morph": "sg|3|pres|subj",
      "mother": "46835",
      "rel": "RC"
    },
    {
      "index": "46849",
      "text": ",",
      "lemma": "--",
      "pos": "$,",
      "morph": "_",
      "mother": "46848",
      "rel": "--"
    },
    {
      "index": "46850",
      "text": "die",
      "lemma": "der",
      "pos": "ART",
      "morph": "nom|sg|fem",
      "mother": "46851",
      "rel": "NK"
    },
    {
      "index": "46851",
      "text": "Bekanntgabe",
      "lemma": "Bekanntgabe",
      "pos": "NN",
      "morph": "nom|sg|fem",
      "mother": "46855",
      "rel": "OA"
    },
    {
      "index": "46852",
      "text": "der",
      "lemma": "der",
      "pos": "ART",
      "morph": "gen|pl|fem",
      "mother": "46854",
      "rel": "NK"
    },
    {
      "index": "46853",
      "text": "realen",
      "lemma": "real",
      "pos": "ADJA",
      "morph": "gen|pl|fem|pos",
      "mother": "46854",
      "rel": "NK"
    },
    {
      "index": "46854",
      "text": "Daten",
      "lemma": "Datum",
      "pos": "NN",
      "morph": "gen|pl|fem",
      "mother": "46851",
      "rel": "AG"
    },
    {
      "index": "46855",
      "text": "hinauszuschieben",
      "lemma": "hinausschieben",
      "pos": "VVPP",
      "morph": "_",
      "mother": "46832",
      "rel": "CJ"
    },
    {
      "index": "46856",
      "text": ".",
      "lemma": "--",
      "pos": "$.",
      "morph": "_",
      "mother": "46855",
      "rel": "--"
    },
    {
      "index": "46857",
      "text": "Ich",
      "lemma": "ich",
      "pos": "PPER",
      "morph": "nom|sg|*|1",
      "mother": "46858",
      "rel": "SB"
    },
    {
      "index": "46858",
      "text": "fordere",
      "lemma": "fordern",
      "pos": "VVFIN",
      "morph": "sg|1|pres|ind",
      "mother": "46856",
      "rel": "--"
    },
    {
      "index": "46859",
      "text": "den",
      "lemma": "der",
      "pos": "ART",
      "morph": "acc|sg|masc",
      "mother": "46860",
      "rel": "NK"
    },
    {
      "index": "46860",
      "text": "Kommissar",
      "lemma": "Kommissar",
      "pos": "NN",
      "morph": "acc|sg|masc",
      "mother": "46858",
      "rel": "OA"
    },
    {
      "index": "46861",
      "text": "auf",
      "lemma": "auf",
      "pos": "PTKVZ",
      "morph": "_",
      "mother": "46858",
      "rel": "SVP"
    },
    {
      "index": "46862",
      "text": ",",
      "lemma": "--",
      "pos": "$,",
      "morph": "_",
      "mother": "46861",
      "rel": "--"
    },
    {
      "index": "46863",
      "text": "sich",
      "lemma": "sich",
      "pos": "PRF",
      "morph": "acc|pl|3",
      "mother": "46869",
      "rel": "OA"
    },
    {
      "index": "46864",
      "text": "klipp",
      "lemma": "klipp",
      "pos": "ADJD",
      "morph": "pos",
      "mother": "46869",
      "rel": "MO"
    },
    {
      "index": "46865",
      "text": "und",
      "lemma": "und",
      "pos": "KON",
      "morph": "_",
      "mother": "46864",
      "rel": "CD"
    },
    {
      "index": "46866",
      "text": "klar",
      "lemma": "klar",
      "pos": "ADJD",
      "morph": "pos",
      "mother": "46865",
      "rel": "CJ"
    },
    {
      "index": "46867",
      "text": "dazu",
      "lemma": "dazu",
      "pos": "PROAV",
      "morph": "_",
      "mother": "46869",
      "rel": "OP"
    },
    {
      "index": "46868",
      "text": "zu",
      "lemma": "zu",
      "pos": "PTKZU",
      "morph": "_",
      "mother": "46869",
      "rel": "PM"
    },
    {
      "index": "46869",
      "text": "\u00e4u\u00dfern",
      "lemma": "\u00e4u\u00dfern",
      "pos": "VVINF",
      "morph": "_",
      "mother": "46858",
      "rel": "OC"
    },
    {
      "index": "46870",
      "text": ",",
      "lemma": "--",
      "pos": "$,",
      "morph": "_",
      "mother": "46869",
      "rel": "--"
    },
    {
      "index": "46871",
      "text": "inwieweit",
      "lemma": "inwieweit",
      "pos": "PWAV",
      "morph": "_",
      "mother": "46876",
      "rel": "MO"
    },
    {
      "index": "46872",
      "text": "er",
      "lemma": "er",
      "pos": "PPER",
      "morph": "nom|sg|masc|3",
      "mother": "46877",
      "rel": "SB"
    },
    {
      "index": "46873",
      "text": "in",
      "lemma": "in",
      "pos": "APPR",
      "morph": "_",
      "mother": "46876",
      "rel": "OP"
    },
    {
      "index": "46874",
      "text": "diese",
      "lemma": "dieser",
      "pos": "PDAT",
      "morph": "acc|sg|fem",
      "mother": "46875",
      "rel": "NK"
    },
    {
      "index": "46875",
      "text": "Sache",
      "lemma": "Sache",
      "pos": "NN",
      "morph": "acc|sg|fem",
      "mother": "46873",
      "rel": "NK"
    },
    {
      "index": "46876",
      "text": "verwickelt",
      "lemma": "verwickeln",
      "pos": "VVPP",
      "morph": "_",
      "mother": "46877",
      "rel": "OC"
    },
    {
      "index": "46877",
      "text": "war",
      "lemma": "sein",
      "pos": "VAFIN",
      "morph": "sg|3|past|ind",
      "mother": "46867",
      "rel": "RE"
    },
    {
      "index": "46878",
      "text": ".",
      "lemma": "--",
      "pos": "$.",
      "morph": "_",
      "mother": "46877",
      "rel": "--"
    },
    {
      "index": "46879",
      "text": "Des",
      "lemma": "der",
      "pos": "ART",
      "morph": "gen|sg|masc",
      "mother": "46880",
      "rel": "NK"
    },
    {
      "index": "46880",
      "text": "Weiteren",
      "lemma": "weitere",
      "pos": "NN",
      "morph": "gen|sg|masc",
      "mother": "46881",
      "rel": "DA"
    },
    {
      "index": "46881",
      "text": "verlange",
      "lemma": "verlangen",
      "pos": "VVFIN",
      "morph": "sg|1|pres|ind",
      "mother": "46878",
      "rel": "--"
    },
    {
      "index": "46882",
      "text": "ich",
      "lemma": "ich",
      "pos": "PPER",
      "morph": "nom|sg|*|1",
      "mother": "46881",
      "rel": "SB"
    },
    {
      "index": "46883",
      "text": ",",
      "lemma": "--",
      "pos": "$,",
      "morph": "_",
      "mother": "46882",
      "rel": "--"
    },
    {
      "index": "46884",
      "text": "dass",
      "lemma": "dass",
      "pos": "KOUS",
      "morph": "_",
      "mother": "46899",
      "rel": "CP"
    },
    {
      "index": "46885",
      "text": "der",
      "lemma": "der",
      "pos": "ART",
      "morph": "nom|sg|masc",
      "mother": "46887",
      "rel": "NK"
    },
    {
      "index": "46886",
      "text": "ungarische",
      "lemma": "ungarisch",
      "pos": "ADJA",
      "morph": "nom|sg|masc|pos",
      "mother": "46887",
      "rel": "NK"
    },
    {
      "index": "46887",
      "text": "Ministerpr\u00e4sident",
      "lemma": "Ministerpr\u00e4sident",
      "pos": "NN",
      "morph": "nom|sg|masc",
      "mother": "46899",
      "rel": "SB"
    },
    {
      "index": "46888",
      "text": ",",
      "lemma": "--",
      "pos": "$,",
      "morph": "_",
      "mother": "46887",
      "rel": "--"
    },
    {
      "index": "46889",
      "text": "der",
      "lemma": "der",
      "pos": "PRELS",
      "morph": "nom|sg|masc",
      "mother": "46894",
      "rel": "SB"
    },
    {
      "index": "46890",
      "text": "sich",
      "lemma": "sich",
      "pos": "PRF",
      "morph": "acc|sg|3",
      "mother": "46893",
      "rel": "OA"
    },
    {
      "index": "46891",
      "text": "so",
      "lemma": "so",
      "pos": "ADV",
      "morph": "_",
      "mother": "46892",
      "rel": "MO"
    },
    {
      "index": "46892",
      "text": "undemokratisch",
      "lemma": "undemokratisch",
      "pos": "ADJD",
      "morph": "pos",
      "mother": "46893",
      "rel": "MO"
    },
    {
      "index": "46893",
      "text": "verhalten",
      "lemma": "verhalten",
      "pos": "VVPP",
      "morph": "_",
      "mother": "46894",
      "rel": "OC"
    },
    {
      "index": "46894",
      "text": "hat",
      "lemma": "haben",
      "pos": "VAFIN",
      "morph": "sg|3|pres|ind",
      "mother": "46887",
      "rel": "RC"
    },
    {
      "index": "46895",
      "text": ",",
      "lemma": "--",
      "pos": "$,",
      "morph": "_",
      "mother": "46894",
      "rel": "--"
    },
    {
      "index": "46896",
      "text": "von",
      "lemma": "von",
      "pos": "APPR",
      "morph": "_",
      "mother": "46899",
      "rel": "OP"
    },
    {
      "index": "46897",
      "text": "seinem",
      "lemma": "sein",
      "pos": "PPOSAT",
      "morph": "dat|sg|neut",
      "mother": "46898",
      "rel": "NK"
    },
    {
      "index": "46898",
      "text": "Amt",
      "lemma": "Amt",
      "pos": "NN",
      "morph": "dat|sg|neut",
      "mother": "46896",
      "rel": "NK"
    },
    {
      "index": "46899",
      "text": "zur\u00fccktritt",
      "lemma": "zur\u00fccktreten",
      "pos": "VVFIN",
      "morph": "sg|3|pres|ind",
      "mother": "46881",
      "rel": "OC"
    },
    {
      "index": "46900",
      "text": ".",
      "lemma": "--",
      "pos": "$.",
      "morph": "_",
      "mother": "46899",
      "rel": "--"
    },
    {
      "index": "46901",
      "text": "Ich",
      "lemma": "ich",
      "pos": "PPER",
      "morph": "nom|sg|*|1",
      "mother": "46902",
      "rel": "SB"
    },
    {
      "index": "46902",
      "text": "bekunde",
      "lemma": "bekund",
      "pos": "VVFIN",
      "morph": "sg|1|pres|ind",
      "mother": "46900",
      "rel": "--"
    },
    {
      "index": "46903",
      "text": "unsere",
      "lemma": "unser",
      "pos": "PPOSAT",
      "morph": "acc|sg|fem",
      "mother": "46904",
      "rel": "NK"
    },
    {
      "index": "46904",
      "text": "Solidarit\u00e4t",
      "lemma": "Solidarit\u00e4t",
      "pos": "NN",
      "morph": "acc|sg|fem",
      "mother": "46902",
      "rel": "OA"
    },
    {
      "index": "46905",
      "text": "mit",
      "lemma": "mit",
      "pos": "APPR",
      "morph": "_",
      "mother": "46902",
      "rel": "MO"
    },
    {
      "index": "46906",
      "text": "den",
      "lemma": "der",
      "pos": "ART",
      "morph": "dat|pl|*",
      "mother": "46907",
      "rel": "NK"
    },
    {
      "index": "46907",
      "text": "Demonstranten",
      "lemma": "Demonstrant",
      "pos": "NN",
      "morph": "dat|pl|*",
      "mother": "46905",
      "rel": "NK"
    },
    {
      "index": "46908",
      "text": "im",
      "lemma": "in",
      "pos": "APPRART",
      "morph": "dat|sg|neut",
      "mother": "46907",
      "rel": "MNR"
    },
    {
      "index": "46909",
      "text": "ganzen",
      "lemma": "ganz",
      "pos": "ADJA",
      "morph": "dat|sg|neut|pos",
      "mother": "46910",
      "rel": "NK"
    },
    {
      "index": "46910",
      "text": "Lande",
      "lemma": "Land",
      "pos": "NN",
      "morph": "dat|sg|neut",
      "mother": "46908",
      "rel": "NK"
    },
    {
      "index": "46911",
      "text": ".",
      "lemma": "--",
      "pos": "$.",
      "morph": "_",
      "mother": "46910",
      "rel": "--"
    },
    {
      "index": "46912",
      "text": "Ich",
      "lemma": "ich",
      "pos": "PPER",
      "morph": "nom|sg|*|1",
      "mother": "46913",
      "rel": "SB"
    },
    {
      "index": "46913",
      "text": "trage",
      "lemma": "tragen",
      "pos": "VVFIN",
      "morph": "sg|1|pres|ind",
      "mother": "46911",
      "rel": "--"
    },
    {
      "index": "46914",
      "text": "heute",
      "lemma": "heute",
      "pos": "ADV",
      "morph": "_",
      "mother": "46913",
      "rel": "MO"
    },
    {
      "index": "46915",
      "text": "ein",
      "lemma": "ein",
      "pos": "ART",
      "morph": "acc|sg|neut",
      "mother": "46917",
      "rel": "NK"
    },
    {
      "index": "46916",
      "text": "wei\u00dfes",
      "lemma": "wei\u00df",
      "pos": "ADJA",
      "morph": "acc|sg|neut|pos",
      "mother": "46917",
      "rel": "NK"
    },
    {
      "index": "46917",
      "text": "Hemd",
      "lemma": "Hemd",
      "pos": "NN",
      "morph": "acc|sg|neut",
      "mother": "46913",
      "rel": "OA"
    },
    {
      "index": "46918",
      "text": ",",
      "lemma": "--",
      "pos": "$,",
      "morph": "_",
      "mother": "46917",
      "rel": "--"
    },
    {
      "index": "46919",
      "text": "um",
      "lemma": "um",
      "pos": "APPR",
      "morph": "_",
      "mother": "46926",
      "rel": "CP"
    },
    {
      "index": "46920",
      "text": "meine",
      "lemma": "mein",
      "pos": "PPOSAT",
      "morph": "acc|sg|fem",
      "mother": "46921",
      "rel": "NK"
    },
    {
      "index": "46921",
      "text": "Solidarit\u00e4t",
      "lemma": "Solidarit\u00e4t",
      "pos": "NN",
      "morph": "acc|sg|fem",
      "mother": "46926",
      "rel": "OA"
    },
    {
      "index": "46922",
      "text": "mit",
      "lemma": "mit",
      "pos": "APPR",
      "morph": "_",
      "mother": "46921",
      "rel": "MNR"
    },
    {
      "index": "46923",
      "text": "den",
      "lemma": "der",
      "pos": "ART",
      "morph": "dat|pl|masc",
      "mother": "46924",
      "rel": "NK"
    },
    {
      "index": "46924",
      "text": "Menschen",
      "lemma": "Mensch",
      "pos": "NN",
      "morph": "dat|pl|masc",
      "mother": "46922",
      "rel": "NK"
    },
    {
      "index": "46925",
      "text": "zu",
      "lemma": "zu",
      "pos": "PTKZU",
      "morph": "_",
      "mother": "46926",
      "rel": "PM"
    },
    {
      "index": "46926",
      "text": "zeigen",
      "lemma": "zeigen",
      "pos": "VVINF",
      "morph": "_",
      "mother": "46917",
      "rel": "MNR"
    },
    {
      "index": "46927",
      "text": "sowie",
      "lemma": "sowie",
      "pos": "KON",
      "morph": "_",
      "mother": "46926",
      "rel": "CD"
    },
    {
      "index": "46928",
      "text": "meine",
      "lemma": "mein",
      "pos": "PPOSAT",
      "morph": "acc|sg|fem",
      "mother": "46929",
      "rel": "NK"
    },
    {
      "index": "46929",
      "text": "Stimme",
      "lemma": "Stimme",
      "pos": "NN",
      "morph": "acc|sg|fem",
      "mother": "46935",
      "rel": "OA"
    },
    {
      "index": "46930",
      "text": "gegen",
      "lemma": "gegen",
      "pos": "APPR",
      "morph": "_",
      "mother": "46935",
      "rel": "MO"
    },
    {
      "index": "46931",
      "text": "L\u00fcgen",
      "lemma": "L\u00fcge",
      "pos": "NN",
      "morph": "acc|pl|fem",
      "mother": "46930",
      "rel": "NK"
    },
    {
      "index": "46932",
      "text": "und",
      "lemma": "und",
      "pos": "KON",
      "morph": "_",
      "mother": "46931",
      "rel": "CD"
    },
    {
      "index": "46933",
      "text": "Gewalt",
      "lemma": "Gewalt",
      "pos": "NN",
      "morph": "acc|sg|fem",
      "mother": "46932",
      "rel": "CJ"
    },
    {
      "index": "46934",
      "text": "zu",
      "lemma": "zu",
      "pos": "PTKZU",
      "morph": "_",
      "mother": "46935",
      "rel": "PM"
    },
    {
      "index": "46935",
      "text": "erheben",
      "lemma": "erheben",
      "pos": "VVINF",
      "morph": "_",
      "mother": "46927",
      "rel": "CJ"
    },
    {
      "index": "46936",
      "text": ".",
      "lemma": "--",
      "pos": "$.",
      "morph": "_",
      "mother": "46935",
      "rel": "--"
    }
  ],
  "sentences": [
    [
      0,
      3
    ],
    [
      3,
      21
    ],
    [
      21,
      44
    ],
    [
      44,
      56
    ],
    [
      56,
      71
    ],
    [
      71,
      84
    ],
    [
      84,
      98
    ],
    [
      98,
      109
    ],
    [
      109,
      130
    ],
    [
      130,
      149
    ],
    [
      149,
      178
    ],
    [
      178,
      188
    ],
    [
      188,
      216
    ],
    [
      216,
      238
    ],
    [
      238,
      260
    ],
    [
      260,
      271
    ],
    [
      271,
      296
    ]
  ],
  "anaphors": [
    {
      "id": "markable_2740",
      "shellnoun": "undefined",
      "start": 121,
      "end": 122,
      "index": 0
    },
    {
      "id": "markable_2739",
      "shellnoun": "undefined",
      "start": 39,
      "end": 40,
      "index": 1
    }
  ],
  "antecedents": [],
  "ref_instances": []
}