{
  "name": "t_97-10-21_231",
  "lang": "de",
  "tokens": [
    {
      "index": "22392",
      "text": "Ich",
      "lemma": "ich",
      "pos": "PPER",
      "morph": "nom|sg|*|1",
      "mother": "22393",
      "rel": "SB"
    },
    {
      "index": "22393",
      "text": "begr\u00fc\u00dfe",
      "lemma": "begr\u00fc\u00dfen",
      "pos": "VVFIN",
      "morph": "sg|1|pres|ind",
      "mother": "22391",
      "rel": "--"
    },
    {
      "index": "22394",
      "text": "den",
      "lemma": "der",
      "pos": "ART",
      "morph": "acc|sg|masc",
      "mother": "22395",
      "rel": "NK"
    },
    {
      "index": "22395",
      "text": "Bericht",
      "lemma": "Bericht",
      "pos": "NN",
      "morph": "acc|sg|masc",
      "mother": "22393",
      "rel": "OA"
    },
    {
      "index": "22396",
      "text": "des",
      "lemma": "der",
      "pos": "ART",
      "morph": "gen|sg|masc",
      "mother": "22397",
      "rel": "NK"
    },
    {
      "index": "22397",
      "text": "Kommissars",
      "lemma": "Kommissar",
      "pos": "NN",
      "morph": "gen|sg|masc",
      "mother": "22395",
      "rel": "AG"
    },
    {
      "index": "22398",
      "text": "und",
      "lemma": "und",
      "pos": "KON",
      "morph": "_",
      "mother": "22395",
      "rel": "CD"
    },
    {
      "index": "22399",
      "text": "nat\u00fcrlich",
      "lemma": "nat\u00fcrlich",
      "pos": "ADV",
      "morph": "_",
      "mother": "22402",
      "rel": "MO"
    },
    {
      "index": "22400",
      "text": "auch",
      "lemma": "auch",
      "pos": "ADV",
      "morph": "_",
      "mother": "22402",
      "rel": "MO"
    },
    {
      "index": "22401",
      "text": "die",
      "lemma": "der",
      "pos": "ART",
      "morph": "acc|sg|fem",
      "mother": "22402",
      "rel": "NK"
    },
    {
      "index": "22402",
      "text": "Aktion",
      "lemma": "Aktion",
      "pos": "NN",
      "morph": "acc|sg|fem",
      "mother": "22398",
      "rel": "CJ"
    },
    {
      "index": "22403",
      "text": "der",
      "lemma": "der",
      "pos": "ART",
      "morph": "gen|sg|fem",
      "mother": "22404",
      "rel": "NK"
    },
    {
      "index": "22404",
      "text": "Kommission",
      "lemma": "Kommission",
      "pos": "NN",
      "morph": "gen|sg|fem",
      "mother": "22402",
      "rel": "AG"
    },
    {
      "index": "22405",
      "text": ",",
      "lemma": "--",
      "pos": "$,",
      "morph": "_",
      "mother": "22404",
      "rel": "--"
    },
    {
      "index": "22406",
      "text": "denn",
      "lemma": "denn",
      "pos": "KON",
      "morph": "_",
      "mother": "22393",
      "rel": "CD"
    },
    {
      "index": "22407",
      "text": "dies",
      "lemma": "dieser",
      "pos": "PDS",
      "morph": "nom|sg|neut",
      "mother": "22408",
      "rel": "SB"
    },
    {
      "index": "22408",
      "text": "ist",
      "lemma": "sein",
      "pos": "VAFIN",
      "morph": "sg|3|pres|ind",
      "mother": "22406",
      "rel": "CJ"
    },
    {
      "index": "22409",
      "text": "ein",
      "lemma": "ein",
      "pos": "ART",
      "morph": "nom|sg|neut",
      "mother": "22412",
      "rel": "NK"
    },
    {
      "index": "22410",
      "text": "schrecklich",
      "lemma": "schrecklich",
      "pos": "ADJD",
      "morph": "pos",
      "mother": "22411",
      "rel": "MO"
    },
    {
      "index": "22411",
      "text": "wichtiges",
      "lemma": "wichtig",
      "pos": "ADJA",
      "morph": "nom|sg|neut|pos",
      "mother": "22412",
      "rel": "NK"
    },
    {
      "index": "22412",
      "text": "Thema",
      "lemma": "Thema",
      "pos": "NN",
      "morph": "nom|sg|neut",
      "mother": "22408",
      "rel": "PD"
    },
    {
      "index": "22413",
      "text": "und",
      "lemma": "und",
      "pos": "KON",
      "morph": "_",
      "mother": "22412",
      "rel": "CD"
    },
    {
      "index": "22414",
      "text": "eins",
      "lemma": "eins",
      "pos": "PIS",
      "morph": "nom|sg|neut",
      "mother": "22413",
      "rel": "CJ"
    },
    {
      "index": "22415",
      "text": ",",
      "lemma": "--",
      "pos": "$,",
      "morph": "_",
      "mother": "22414",
      "rel": "--"
    },
    {
      "index": "22416",
      "text": "f\u00fcr",
      "lemma": "f\u00fcr",
      "pos": "APPR",
      "morph": "_",
      "mother": "22425",
      "rel": "MO"
    },
    {
      "index": "22417",
      "text": "das",
      "lemma": "der",
      "pos": "PRELS",
      "morph": "acc|sg|neut",
      "mother": "22416",
      "rel": "NK"
    },
    {
      "index": "22418",
      "text": "wir",
      "lemma": "wir",
      "pos": "PPER",
      "morph": "nom|pl|*|1",
      "mother": "22425",
      "rel": "SB"
    },
    {
      "index": "22419",
      "text": "auf",
      "lemma": "auf",
      "pos": "APPR",
      "morph": "_",
      "mother": "22425",
      "rel": "MO"
    },
    {
      "index": "22420",
      "text": "europ\u00e4ischer",
      "lemma": "europ\u00e4isch",
      "pos": "ADJA",
      "morph": "dat|sg|fem|pos",
      "mother": "22421",
      "rel": "NK"
    },
    {
      "index": "22421",
      "text": "Ebene",
      "lemma": "Ebene",
      "pos": "NN",
      "morph": "dat|sg|fem",
      "mother": "22419",
      "rel": "NK"
    },
    {
      "index": "22422",
      "text": "sehr",
      "lemma": "sehr",
      "pos": "ADV",
      "morph": "_",
      "mother": "22425",
      "rel": "MO"
    },
    {
      "index": "22423",
      "text": "viel",
      "lemma": "viel",
      "pos": "PIS",
      "morph": "_",
      "mother": "22424",
      "rel": "OA"
    },
    {
      "index": "22424",
      "text": "tun",
      "lemma": "tun",
      "pos": "VVINF",
      "morph": "_",
      "mother": "22425",
      "rel": "OC"
    },
    {
      "index": "22425",
      "text": "k\u00f6nnen",
      "lemma": "k\u00f6nnen",
      "pos": "VMINF",
      "morph": "_",
      "mother": "22412",
      "rel": "RC"
    },
    {
      "index": "22426",
      "text": ".",
      "lemma": "--",
      "pos": "$.",
      "morph": "_",
      "mother": "22425",
      "rel": "--"
    },
    {
      "index": "22427",
      "text": "Dieses",
      "lemma": "dieser",
      "pos": "PDAT",
      "morph": "acc|sg|neut",
      "mother": "22428",
      "rel": "NK"
    },
    {
      "index": "22428",
      "text": "Jahr",
      "lemma": "Jahr",
      "pos": "NN",
      "morph": "acc|sg|neut",
      "mother": "22434",
      "rel": "MO"
    },
    {
      "index": "22429",
      "text": "hatten",
      "lemma": "haben",
      "pos": "VAFIN",
      "morph": "pl|1|past|ind",
      "mother": "22426",
      "rel": "--"
    },
    {
      "index": "22430",
      "text": "wir",
      "lemma": "wir",
      "pos": "PPER",
      "morph": "nom|pl|*|1",
      "mother": "22429",
      "rel": "SB"
    },
    {
      "index": "22431",
      "text": "die",
      "lemma": "der",
      "pos": "ART",
      "morph": "acc|sg|fem",
      "mother": "22434",
      "rel": "NK"
    },
    {
      "index": "22432",
      "text": "f\u00fcnfte",
      "lemma": "f\u00fcnfter",
      "pos": "ADJA",
      "morph": "acc|sg|fem|pos",
      "mother": "22434",
      "rel": "NK"
    },
    {
      "index": "22433",
      "text": "\"",
      "lemma": "--",
      "pos": "$(",
      "morph": "_",
      "mother": "22432",
      "rel": "--"
    },
    {
      "index": "22434",
      "text": "Europa",
      "lemma": "Europa",
      "pos": "NE",
      "morph": "nom|sg|neut",
      "mother": "22429",
      "rel": "OC"
    },
    {
      "index": "22435",
      "text": "gegen",
      "lemma": "gegen",
      "pos": "APPR",
      "morph": "_",
      "mother": "22434",
      "rel": "MNR"
    },
    {
      "index": "22436",
      "text": "Krebs",
      "lemma": "Krebs",
      "pos": "NE",
      "morph": "acc|sg|masc",
      "mother": "22437",
      "rel": "PNC"
    },
    {
      "index": "22437",
      "text": "Woche",
      "lemma": "Woche",
      "pos": "NN",
      "morph": "acc|sg|masc",
      "mother": "22435",
      "rel": "NK"
    },
    {
      "index": "22438",
      "text": "\"",
      "lemma": "--",
      "pos": "$(",
      "morph": "_",
      "mother": "22437",
      "rel": "--"
    },
    {
      "index": "22439",
      "text": "und",
      "lemma": "und",
      "pos": "KON",
      "morph": "_",
      "mother": "22429",
      "rel": "CD"
    },
    {
      "index": "22440",
      "text": "Priorit\u00e4tsstufe",
      "lemma": "Priorit\u00e4tsstufe",
      "pos": "NN",
      "morph": "nom|pl|masc",
      "mother": "22442",
      "rel": "SB"
    },
    {
      "index": "22441",
      "text": "zwei",
      "lemma": "zwei",
      "pos": "CARD",
      "morph": "_",
      "mother": "22440",
      "rel": "NK"
    },
    {
      "index": "22442",
      "text": "war",
      "lemma": "sein",
      "pos": "VAFIN",
      "morph": "sg|3|past|ind",
      "mother": "22439",
      "rel": "CJ"
    },
    {
      "index": "22443",
      "text": "hierbei",
      "lemma": "hierbei",
      "pos": "ADV",
      "morph": "_",
      "mother": "22442",
      "rel": "MO"
    },
    {
      "index": "22444",
      "text": "bestimmt",
      "lemma": "bestimmen",
      "pos": "ADJD",
      "morph": "pos",
      "mother": "22442",
      "rel": "PD"
    },
    {
      "index": "22445",
      "text": "f\u00fcr",
      "lemma": "f\u00fcr",
      "pos": "APPR",
      "morph": "_",
      "mother": "22444",
      "rel": "MO"
    },
    {
      "index": "22446",
      "text": "Gesundheit",
      "lemma": "Gesundheit",
      "pos": "NN",
      "morph": "acc|sg|fem",
      "mother": "22445",
      "rel": "NK"
    },
    {
      "index": "22447",
      "text": ",",
      "lemma": "--",
      "pos": "$,",
      "morph": "_",
      "mother": "22446",
      "rel": "--"
    },
    {
      "index": "22448",
      "text": "Erziehung",
      "lemma": "Erziehung",
      "pos": "NN",
      "morph": "acc|sg|fem",
      "mother": "22446",
      "rel": "CJ"
    },
    {
      "index": "22449",
      "text": "und",
      "lemma": "und",
      "pos": "KON",
      "morph": "_",
      "mother": "22448",
      "rel": "CD"
    },
    {
      "index": "22450",
      "text": "Information",
      "lemma": "Information",
      "pos": "NN",
      "morph": "acc|sg|fem",
      "mother": "22449",
      "rel": "CJ"
    },
    {
      "index": "22451",
      "text": ".",
      "lemma": "--",
      "pos": "$.",
      "morph": "_",
      "mother": "22450",
      "rel": "--"
    },
    {
      "index": "22452",
      "text": "Sehr",
      "lemma": "sehr",
      "pos": "ADV",
      "morph": "_",
      "mother": "22453",
      "rel": "MO"
    },
    {
      "index": "22453",
      "text": "geehrter",
      "lemma": "geehrt",
      "pos": "ADJA",
      "morph": "nom|sg|masc|pos",
      "mother": "22454",
      "rel": "NK"
    },
    {
      "index": "22454",
      "text": "Kommissar",
      "lemma": "Kommissar",
      "pos": "NN",
      "morph": "nom|sg|masc",
      "mother": "22494",
      "rel": "PD"
    },
    {
      "index": "22455",
      "text": ",",
      "lemma": "--",
      "pos": "$,",
      "morph": "_",
      "mother": "22454",
      "rel": "--"
    },
    {
      "index": "22456",
      "text": "als",
      "lemma": "als",
      "pos": "APPR",
      "morph": "_",
      "mother": "22460",
      "rel": "MO"
    },
    {
      "index": "22457",
      "text": "Teil",
      "lemma": "Teil",
      "pos": "NN",
      "morph": "nom|sg|masc",
      "mother": "22456",
      "rel": "NK"
    },
    {
      "index": "22458",
      "text": "dieser",
      "lemma": "dieser",
      "pos": "PDAT",
      "morph": "nom|sg|masc",
      "mother": "22460",
      "rel": "NK"
    },
    {
      "index": "22459",
      "text": "\"",
      "lemma": "--",
      "pos": "$(",
      "morph": "_",
      "mother": "22458",
      "rel": "--"
    },
    {
      "index": "22460",
      "text": "Woche",
      "lemma": "Woche",
      "pos": "NN",
      "morph": "acc|sg|fem",
      "mother": "22454",
      "rel": "PAR"
    },
    {
      "index": "22461",
      "text": "\"",
      "lemma": "--",
      "pos": "$(",
      "morph": "_",
      "mother": "22460",
      "rel": "--"
    },
    {
      "index": "22462",
      "text": "habe",
      "lemma": "haben",
      "pos": "VAFIN",
      "morph": "sg|1|pres|ind",
      "mother": "22451",
      "rel": "--"
    },
    {
      "index": "22463",
      "text": "ich",
      "lemma": "ich",
      "pos": "PPER",
      "morph": "nom|sg|*|1",
      "mother": "22462",
      "rel": "SB"
    },
    {
      "index": "22464",
      "text": "eines",
      "lemma": "ein",
      "pos": "PIS",
      "morph": "acc|sg|neut",
      "mother": "22471",
      "rel": "OA"
    },
    {
      "index": "22465",
      "text": "der",
      "lemma": "der",
      "pos": "ART",
      "morph": "gen|pl|neut",
      "mother": "22467",
      "rel": "NK"
    },
    {
      "index": "22466",
      "text": "\u00f6rtlichen",
      "lemma": "\u00f6rtlich",
      "pos": "ADJA",
      "morph": "gen|pl|neut|pos",
      "mother": "22467",
      "rel": "NK"
    },
    {
      "index": "22467",
      "text": "Krankenh\u00e4user",
      "lemma": "Krankenhaus",
      "pos": "NN",
      "morph": "gen|pl|neut",
      "mother": "22464",
      "rel": "AG"
    },
    {
      "index": "22468",
      "text": "in",
      "lemma": "in",
      "pos": "APPR",
      "morph": "_",
      "mother": "22471",
      "rel": "MO"
    },
    {
      "index": "22469",
      "text": "meinem",
      "lemma": "mein",
      "pos": "PPOSAT",
      "morph": "dat|sg|neut",
      "mother": "22470",
      "rel": "NK"
    },
    {
      "index": "22470",
      "text": "Wahlkreis",
      "lemma": "Wahlkreis",
      "pos": "NN",
      "morph": "dat|sg|neut",
      "mother": "22468",
      "rel": "NK"
    },
    {
      "index": "22471",
      "text": "besucht",
      "lemma": "besuchen",
      "pos": "VVPP",
      "morph": "_",
      "mother": "22462",
      "rel": "OC"
    },
    {
      "index": "22472",
      "text": "-",
      "lemma": "--",
      "pos": "$(",
      "morph": "_",
      "mother": "22471",
      "rel": "--"
    },
    {
      "index": "22473",
      "text": "eigentlich",
      "lemma": "eigentlich",
      "pos": "ADV",
      "morph": "_",
      "mother": "22476",
      "rel": "MO"
    },
    {
      "index": "22474",
      "text": "die",
      "lemma": "der",
      "pos": "ART",
      "morph": "acc|sg|fem",
      "mother": "22476",
      "rel": "NK"
    },
    {
      "index": "22475",
      "text": "gr\u00f6\u00dfte",
      "lemma": "gro\u00df",
      "pos": "ADJA",
      "morph": "acc|sg|fem|sup",
      "mother": "22476",
      "rel": "NK"
    },
    {
      "index": "22476",
      "text": "Krebseinheit",
      "lemma": "Krebseinheit",
      "pos": "NN",
      "morph": "acc|sg|fem",
      "mother": "22471",
      "rel": "PAR"
    },
    {
      "index": "22477",
      "text": "aller",
      "lemma": "aller",
      "pos": "PIAT",
      "morph": "gen|pl|neut",
      "mother": "22479",
      "rel": "NK"
    },
    {
      "index": "22478",
      "text": "\u00f6rtlichen",
      "lemma": "\u00f6rtlich",
      "pos": "ADJA",
      "morph": "gen|pl|neut|pos",
      "mother": "22479",
      "rel": "NK"
    },
    {
      "index": "22479",
      "text": "Krankenh\u00e4user",
      "lemma": "Krankenhaus",
      "pos": "NN",
      "morph": "gen|pl|neut",
      "mother": "22476",
      "rel": "AG"
    },
    {
      "index": "22480",
      "text": "-",
      "lemma": "--",
      "pos": "$(",
      "morph": "_",
      "mother": "22479",
      "rel": "--"
    },
    {
      "index": "22481",
      "text": "in",
      "lemma": "in",
      "pos": "APPR",
      "morph": "_",
      "mother": "22476",
      "rel": "MNR"
    },
    {
      "index": "22482",
      "text": "einer",
      "lemma": "ein",
      "pos": "ART",
      "morph": "dat|sg|fem",
      "mother": "22484",
      "rel": "NK"
    },
    {
      "index": "22483",
      "text": "mittelgro\u00dfen",
      "lemma": "mittelgro\u00df",
      "pos": "ADJA",
      "morph": "dat|sg|fem|pos",
      "mother": "22484",
      "rel": "NK"
    },
    {
      "index": "22484",
      "text": "Stadt",
      "lemma": "Stadt",
      "pos": "NN",
      "morph": "dat|sg|fem",
      "mother": "22481",
      "rel": "NK"
    },
    {
      "index": "22485",
      "text": ",",
      "lemma": "--",
      "pos": "$,",
      "morph": "_",
      "mother": "22484",
      "rel": "--"
    },
    {
      "index": "22486",
      "text": "genau",
      "lemma": "genau",
      "pos": "ADJD",
      "morph": "pos",
      "mother": "22487",
      "rel": "MO"
    },
    {
      "index": "22487",
      "text": "deshalb",
      "lemma": "deshalb",
      "pos": "PROAV",
      "morph": "_",
      "mother": "22471",
      "rel": "MO"
    },
    {
      "index": "22488",
      "text": ",",
      "lemma": "--",
      "pos": "$,",
      "morph": "_",
      "mother": "22487",
      "rel": "--"
    },
    {
      "index": "22489",
      "text": "weil",
      "lemma": "weil",
      "pos": "KOUS",
      "morph": "_",
      "mother": "22495",
      "rel": "CP"
    },
    {
      "index": "22490",
      "text": "Europa",
      "lemma": "Europa",
      "pos": "NE",
      "morph": "nom|sg|neut",
      "mother": "22495",
      "rel": "SB"
    },
    {
      "index": "22491",
      "text": "gegen",
      "lemma": "gegen",
      "pos": "APPR",
      "morph": "_",
      "mother": "22494",
      "rel": "MO"
    },
    {
      "index": "22492",
      "text": "Krebs",
      "lemma": "Krebs",
      "pos": "NE",
      "morph": "acc|sg|masc",
      "mother": "22491",
      "rel": "NK"
    },
    {
      "index": "22493",
      "text": "Woche",
      "lemma": "Woche",
      "pos": "NN",
      "morph": "acc|sg|masc",
      "mother": "22494",
      "rel": "PD"
    },
    {
      "index": "22494",
      "text": "gewesen",
      "lemma": "sein",
      "pos": "VAPP",
      "morph": "_",
      "mother": "22495",
      "rel": "OC"
    },
    {
      "index": "22495",
      "text": "ist",
      "lemma": "sein",
      "pos": "VAFIN",
      "morph": "sg|3|pres|ind",
      "mother": "22487",
      "rel": "RE"
    },
    {
      "index": "22496",
      "text": ".",
      "lemma": "--",
      "pos": "$.",
      "morph": "_",
      "mother": "22495",
      "rel": "--"
    },
    {
      "index": "22497",
      "text": "Ich",
      "lemma": "ich",
      "pos": "PPER",
      "morph": "nom|sg|*|1",
      "mother": "22498",
      "rel": "SB"
    },
    {
      "index": "22498",
      "text": "bin",
      "lemma": "sein",
      "pos": "VAFIN",
      "morph": "sg|1|pres|ind",
      "mother": "22496",
      "rel": "--"
    },
    {
      "index": "22499",
      "text": "besonders",
      "lemma": "besonders",
      "pos": "ADV",
      "morph": "_",
      "mother": "22500",
      "rel": "MO"
    },
    {
      "index": "22500",
      "text": "traurig",
      "lemma": "traurig",
      "pos": "ADJD",
      "morph": "pos",
      "mother": "22501",
      "rel": "PD"
    },
    {
      "index": "22501",
      "text": "gewesen",
      "lemma": "sein",
      "pos": "VAPP",
      "morph": "_",
      "mother": "22498",
      "rel": "OC"
    },
    {
      "index": "22502",
      "text": ",",
      "lemma": "--",
      "pos": "$,",
      "morph": "_",
      "mother": "22501",
      "rel": "--"
    },
    {
      "index": "22503",
      "text": "da",
      "lemma": "da",
      "pos": "KOUS",
      "morph": "_",
      "mother": "22515",
      "rel": "CP"
    },
    {
      "index": "22504",
      "text": "dieses",
      "lemma": "dieser",
      "pos": "PDAT",
      "morph": "gen|sg|masc",
      "mother": "22505",
      "rel": "NK"
    },
    {
      "index": "22505",
      "text": "Krankenhaus",
      "lemma": "Krankenhaus",
      "pos": "NN",
      "morph": "gen|sg|masc",
      "mother": "22515",
      "rel": "SB"
    },
    {
      "index": "22506",
      "text": "noch",
      "lemma": "noch",
      "pos": "ADV",
      "morph": "_",
      "mother": "22507",
      "rel": "MO"
    },
    {
      "index": "22507",
      "text": "niemals",
      "lemma": "niemals",
      "pos": "ADV",
      "morph": "_",
      "mother": "22514",
      "rel": "MO"
    },
    {
      "index": "22508",
      "text": "von",
      "lemma": "von",
      "pos": "APPR",
      "morph": "_",
      "mother": "22514",
      "rel": "SBP"
    },
    {
      "index": "22509",
      "text": "dieser",
      "lemma": "dieser",
      "pos": "PDAT",
      "morph": "dat|sg|fem",
      "mother": "22510",
      "rel": "NK"
    },
    {
      "index": "22510",
      "text": "Europa",
      "lemma": "Europa",
      "pos": "NE",
      "morph": "dat|sg|fem",
      "mother": "22508",
      "rel": "NK"
    },
    {
      "index": "22511",
      "text": "gegen",
      "lemma": "gegen",
      "pos": "APPR",
      "morph": "_",
      "mother": "22514",
      "rel": "OP"
    },
    {
      "index": "22512",
      "text": "Krebs",
      "lemma": "Krebs",
      "pos": "NN",
      "morph": "acc|sg|masc",
      "mother": "22511",
      "rel": "NK"
    },
    {
      "index": "22513",
      "text": "Woche",
      "lemma": "Woche",
      "pos": "NN",
      "morph": "acc|sg|fem",
      "mother": "22512",
      "rel": "NK"
    },
    {
      "index": "22514",
      "text": "geh\u00f6rt",
      "lemma": "geh\u00f6ren",
      "pos": "VVPP",
      "morph": "_",
      "mother": "22515",
      "rel": "OC"
    },
    {
      "index": "22515",
      "text": "hatte",
      "lemma": "haben",
      "pos": "VAFIN",
      "morph": "sg|3|past|ind",
      "mother": "22501",
      "rel": "MO"
    },
    {
      "index": "22516",
      "text": ",",
      "lemma": "--",
      "pos": "$,",
      "morph": "_",
      "mother": "22515",
      "rel": "--"
    },
    {
      "index": "22517",
      "text": "obwohl",
      "lemma": "obwohl",
      "pos": "KOUS",
      "morph": "_",
      "mother": "22525",
      "rel": "CP"
    },
    {
      "index": "22518",
      "text": "wir",
      "lemma": "wir",
      "pos": "PPER",
      "morph": "nom|pl|*|1",
      "mother": "22525",
      "rel": "SB"
    },
    {
      "index": "22519",
      "text": "schon",
      "lemma": "schon",
      "pos": "ADV",
      "morph": "_",
      "mother": "22524",
      "rel": "MO"
    },
    {
      "index": "22520",
      "text": "in",
      "lemma": "in",
      "pos": "APPR",
      "morph": "_",
      "mother": "22524",
      "rel": "MO"
    },
    {
      "index": "22521",
      "text": "unserem",
      "lemma": "unser",
      "pos": "PPOSAT",
      "morph": "dat|sg|neut",
      "mother": "22523",
      "rel": "NK"
    },
    {
      "index": "22522",
      "text": "f\u00fcnften",
      "lemma": "f\u00fcnfter",
      "pos": "ADJA",
      "morph": "dat|sg|neut|pos",
      "mother": "22523",
      "rel": "NK"
    },
    {
      "index": "22523",
      "text": "Jahr",
      "lemma": "Jahr",
      "pos": "NN",
      "morph": "dat|sg|neut",
      "mother": "22520",
      "rel": "NK"
    },
    {
      "index": "22524",
      "text": "gewesen",
      "lemma": "sein",
      "pos": "VAPP",
      "morph": "_",
      "mother": "22525",
      "rel": "OC"
    },
    {
      "index": "22525",
      "text": "sind",
      "lemma": "sein",
      "pos": "VAFIN",
      "morph": "pl|3|pres|ind",
      "mother": "22501",
      "rel": "MO"
    },
    {
      "index": "22526",
      "text": "und",
      "lemma": "und",
      "pos": "KON",
      "morph": "_",
      "mother": "22525",
      "rel": "CD"
    },
    {
      "index": "22527",
      "text": "das",
      "lemma": "der",
      "pos": "ART",
      "morph": "nom|sg|neut",
      "mother": "22528",
      "rel": "NK"
    },
    {
      "index": "22528",
      "text": "Krankenhaus",
      "lemma": "Krankenhaus",
      "pos": "NN",
      "morph": "nom|sg|neut",
      "mother": "22529",
      "rel": "SB"
    },
    {
      "index": "22529",
      "text": "bestimmt",
      "lemma": "bestimmen",
      "pos": "VVFIN",
      "morph": "sg|3|pres|ind",
      "mother": "22526",
      "rel": "CJ"
    },
    {
      "index": "22530",
      "text": "noch",
      "lemma": "noch",
      "pos": "ADV",
      "morph": "_",
      "mother": "22531",
      "rel": "MO"
    },
    {
      "index": "22531",
      "text": "nie",
      "lemma": "nie",
      "pos": "ADV",
      "morph": "_",
      "mother": "22529",
      "rel": "MO"
    },
    {
      "index": "22532",
      "text": "etwas",
      "lemma": "etwas",
      "pos": "PIS",
      "morph": "*|*|neut",
      "mother": "22537",
      "rel": "SB"
    },
    {
      "index": "22533",
      "text": "von",
      "lemma": "von",
      "pos": "APPR",
      "morph": "_",
      "mother": "22536",
      "rel": "SBP"
    },
    {
      "index": "22534",
      "text": "dem",
      "lemma": "der",
      "pos": "ART",
      "morph": "dat|sg|masc",
      "mother": "22535",
      "rel": "NK"
    },
    {
      "index": "22535",
      "text": "Zehnpunkteplan",
      "lemma": "Zehnpunkteplan",
      "pos": "NN",
      "morph": "dat|sg|masc",
      "mother": "22533",
      "rel": "NK"
    },
    {
      "index": "22536",
      "text": "geh\u00f6rt",
      "lemma": "geh\u00f6ren",
      "pos": "VVPP",
      "morph": "_",
      "mother": "22537",
      "rel": "OC"
    },
    {
      "index": "22537",
      "text": "hatte",
      "lemma": "haben",
      "pos": "VAFIN",
      "morph": "sg|3|past|ind",
      "mother": "22529",
      "rel": "MO"
    },
    {
      "index": "22538",
      "text": ",",
      "lemma": "--",
      "pos": "$,",
      "morph": "_",
      "mother": "22537",
      "rel": "--"
    },
    {
      "index": "22539",
      "text": "den",
      "lemma": "der",
      "pos": "PRELS",
      "morph": "acc|sg|masc",
      "mother": "22545",
      "rel": "OA"
    },
    {
      "index": "22540",
      "text": "ich",
      "lemma": "ich",
      "pos": "PPER",
      "morph": "nom|sg|*|1",
      "mother": "22545",
      "rel": "SB"
    },
    {
      "index": "22541",
      "text": "bei",
      "lemma": "bei",
      "pos": "APPR",
      "morph": "_",
      "mother": "22544",
      "rel": "MO"
    },
    {
      "index": "22542",
      "text": "meinem",
      "lemma": "mein",
      "pos": "PPOSAT",
      "morph": "dat|sg|masc",
      "mother": "22543",
      "rel": "NK"
    },
    {
      "index": "22543",
      "text": "Besuch",
      "lemma": "Besuch",
      "pos": "NN",
      "morph": "dat|sg|masc",
      "mother": "22541",
      "rel": "NK"
    },
    {
      "index": "22544",
      "text": "\u00fcberreichen",
      "lemma": "\u00fcberreichen",
      "pos": "VVINF",
      "morph": "_",
      "mother": "22545",
      "rel": "OC"
    },
    {
      "index": "22545",
      "text": "sollte",
      "lemma": "sollen",
      "pos": "VMFIN",
      "morph": "sg|3|past|ind",
      "mother": "22535",
      "rel": "RC"
    },
    {
      "index": "22546",
      "text": ".",
      "lemma": "--",
      "pos": "$.",
      "morph": "_",
      "mother": "22545",
      "rel": "--"
    },
    {
      "index": "22547",
      "text": "Ich",
      "lemma": "ich",
      "pos": "PPER",
      "morph": "nom|sg|*|1",
      "mother": "22548",
      "rel": "SB"
    },
    {
      "index": "22548",
      "text": "frage",
      "lemma": "fragen",
      "pos": "VVFIN",
      "morph": "sg|1|pres|ind",
      "mother": "22546",
      "rel": "--"
    },
    {
      "index": "22549",
      "text": "mich",
      "lemma": "mich",
      "pos": "PRF",
      "morph": "acc|sg|1",
      "mother": "22548",
      "rel": "OA"
    },
    {
      "index": "22550",
      "text": ",",
      "lemma": "--",
      "pos": "$,",
      "morph": "_",
      "mother": "22549",
      "rel": "--"
    },
    {
      "index": "22551",
      "text": "ob",
      "lemma": "ob",
      "pos": "KOUS",
      "morph": "_",
      "mother": "22557",
      "rel": "CP"
    },
    {
      "index": "22552",
      "text": "der",
      "lemma": "der",
      "pos": "ART",
      "morph": "nom|sg|masc",
      "mother": "22553",
      "rel": "NK"
    },
    {
      "index": "22553",
      "text": "Kommissar",
      "lemma": "Kommissar",
      "pos": "NN",
      "morph": "nom|sg|masc",
      "mother": "22557",
      "rel": "SB"
    },
    {
      "index": "22554",
      "text": "das",
      "lemma": "der",
      "pos": "ART",
      "morph": "acc|sg|neut",
      "mother": "22555",
      "rel": "NK"
    },
    {
      "index": "22555",
      "text": "Ausma\u00df",
      "lemma": "Ausma\u00df",
      "pos": "NN",
      "morph": "acc|sg|neut",
      "mother": "22556",
      "rel": "OA"
    },
    {
      "index": "22556",
      "text": "sehen",
      "lemma": "sehen",
      "pos": "VVINF",
      "morph": "_",
      "mother": "22557",
      "rel": "OC"
    },
    {
      "index": "22557",
      "text": "will",
      "lemma": "wollen",
      "pos": "VMFIN",
      "morph": "sg|3|pres|ind",
      "mother": "22548",
      "rel": "SB"
    },
    {
      "index": "22558",
      "text": ",",
      "lemma": "--",
      "pos": "$,",
      "morph": "_",
      "mother": "22557",
      "rel": "--"
    },
    {
      "index": "22559",
      "text": "in",
      "lemma": "in",
      "pos": "APPR",
      "morph": "_",
      "mother": "22563",
      "rel": "MO"
    },
    {
      "index": "22560",
      "text": "dem",
      "lemma": "der",
      "pos": "PRELS",
      "morph": "dat|sg|masc",
      "mother": "22559",
      "rel": "NK"
    },
    {
      "index": "22561",
      "text": "diese",
      "lemma": "dieser",
      "pos": "PDAT",
      "morph": "nom|pl|fem",
      "mother": "22562",
      "rel": "NK"
    },
    {
      "index": "22562",
      "text": "Informationen",
      "lemma": "Information",
      "pos": "NN",
      "morph": "nom|pl|fem",
      "mother": "22563",
      "rel": "OA"
    },
    {
      "index": "22563",
      "text": "hinauskommen",
      "lemma": "hinauskommen",
      "pos": "VVFIN",
      "morph": "pl|3|pres|ind",
      "mother": "22555",
      "rel": "RC"
    },
    {
      "index": "22564",
      "text": ".",
      "lemma": "--",
      "pos": "$.",
      "morph": "_",
      "mother": "22563",
      "rel": "--"
    },
    {
      "index": "22565",
      "text": "In",
      "lemma": "in",
      "pos": "APPR",
      "morph": "_",
      "mother": "22570",
      "rel": "MO"
    },
    {
      "index": "22566",
      "text": "manchen",
      "lemma": "mancher",
      "pos": "PIAT",
      "morph": "dat|pl|neut",
      "mother": "22567",
      "rel": "NK"
    },
    {
      "index": "22567",
      "text": "Unterlagen",
      "lemma": "Unterlage",
      "pos": "NN",
      "morph": "dat|pl|neut",
      "mother": "22565",
      "rel": "NK"
    },
    {
      "index": "22568",
      "text": "des",
      "lemma": "der",
      "pos": "ART",
      "morph": "gen|sg|masc",
      "mother": "22569",
      "rel": "NK"
    },
    {
      "index": "22569",
      "text": "Kommissars",
      "lemma": "Kommissar",
      "pos": "NN",
      "morph": "gen|sg|masc",
      "mother": "22567",
      "rel": "AG"
    },
    {
      "index": "22570",
      "text": "kann",
      "lemma": "k\u00f6nnen",
      "pos": "VMFIN",
      "morph": "sg|1|pres|ind",
      "mother": "22564",
      "rel": "--"
    },
    {
      "index": "22571",
      "text": "ich",
      "lemma": "ich",
      "pos": "PPER",
      "morph": "nom|sg|*|1",
      "mother": "22570",
      "rel": "SB"
    },
    {
      "index": "22572",
      "text": "lesen",
      "lemma": "lesen",
      "pos": "VVINF",
      "morph": "_",
      "mother": "22570",
      "rel": "OC"
    },
    {
      "index": "22573",
      "text": ",",
      "lemma": "--",
      "pos": "$,",
      "morph": "_",
      "mother": "22572",
      "rel": "--"
    },
    {
      "index": "22574",
      "text": "da\u00df",
      "lemma": "da\u00df",
      "pos": "KOUS",
      "morph": "_",
      "mother": "22582",
      "rel": "CP"
    },
    {
      "index": "22575",
      "text": "eine",
      "lemma": "ein",
      "pos": "ART",
      "morph": "nom|sg|fem",
      "mother": "22577",
      "rel": "NK"
    },
    {
      "index": "22576",
      "text": "\u00f6ffentliche",
      "lemma": "\u00f6ffentlich",
      "pos": "ADJA",
      "morph": "nom|sg|fem|pos",
      "mother": "22577",
      "rel": "NK"
    },
    {
      "index": "22577",
      "text": "Einladung",
      "lemma": "Einladung",
      "pos": "NN",
      "morph": "nom|sg|fem",
      "mother": "22582",
      "rel": "SB"
    },
    {
      "index": "22578",
      "text": "als",
      "lemma": "als",
      "pos": "APPR",
      "morph": "_",
      "mother": "22580",
      "rel": "MO"
    },
    {
      "index": "22579",
      "text": "Angebot",
      "lemma": "Angebot",
      "pos": "NN",
      "morph": "nom|sg|neut",
      "mother": "22578",
      "rel": "NK"
    },
    {
      "index": "22580",
      "text": "herausgegeben",
      "lemma": "herausgeben",
      "pos": "VVPP",
      "morph": "_",
      "mother": "22581",
      "rel": "OC"
    },
    {
      "index": "22581",
      "text": "worden",
      "lemma": "werden",
      "pos": "VAPP",
      "morph": "_",
      "mother": "22582",
      "rel": "OC"
    },
    {
      "index": "22582",
      "text": "ist",
      "lemma": "sein",
      "pos": "VAFIN",
      "morph": "sg|3|pres|ind",
      "mother": "22572",
      "rel": "OC"
    },
    {
      "index": "22583",
      "text": "und",
      "lemma": "und",
      "pos": "KON",
      "morph": "_",
      "mother": "22582",
      "rel": "CD"
    },
    {
      "index": "22584",
      "text": "eine",
      "lemma": "ein",
      "pos": "ART",
      "morph": "nom|sg|fem",
      "mother": "22586",
      "rel": "NK"
    },
    {
      "index": "22585",
      "text": "professionelle",
      "lemma": "professionell",
      "pos": "ADJA",
      "morph": "nom|sg|fem|pos",
      "mother": "22586",
      "rel": "NK"
    },
    {
      "index": "22586",
      "text": "Kommunikationsvertretung",
      "lemma": "Kommunikationsvertretung",
      "pos": "NN",
      "morph": "nom|sg|fem",
      "mother": "22594",
      "rel": "SB"
    },
    {
      "index": "22587",
      "text": "mit",
      "lemma": "mit",
      "pos": "APPR",
      "morph": "_",
      "mother": "22593",
      "rel": "MO"
    },
    {
      "index": "22588",
      "text": "B\u00fcros",
      "lemma": "B\u00fcro",
      "pos": "NN",
      "morph": "dat|pl|neut",
      "mother": "22587",
      "rel": "NK"
    },
    {
      "index": "22589",
      "text": "in",
      "lemma": "in",
      "pos": "APPR",
      "morph": "_",
      "mother": "22593",
      "rel": "MO"
    },
    {
      "index": "22590",
      "text": "fast",
      "lemma": "fast",
      "pos": "ADV",
      "morph": "_",
      "mother": "22591",
      "rel": "MO"
    },
    {
      "index": "22591",
      "text": "allen",
      "lemma": "aller",
      "pos": "PIAT",
      "morph": "dat|pl|masc",
      "mother": "22592",
      "rel": "NK"
    },
    {
      "index": "22592",
      "text": "Mitgliedstaaten",
      "lemma": "Mitgliedstaat",
      "pos": "NN",
      "morph": "dat|pl|masc",
      "mother": "22589",
      "rel": "NK"
    },
    {
      "index": "22593",
      "text": "ausgesucht",
      "lemma": "aussuchen",
      "pos": "VVPP",
      "morph": "_",
      "mother": "22594",
      "rel": "OC"
    },
    {
      "index": "22594",
      "text": "wurde",
      "lemma": "werden",
      "pos": "VAFIN",
      "morph": "sg|3|past|ind",
      "mother": "22583",
      "rel": "CJ"
    },
    {
      "index": "22595",
      "text": ".",
      "lemma": "--",
      "pos": "$.",
      "morph": "_",
      "mother": "22594",
      "rel": "--"
    },
    {
      "index": "22596",
      "text": "Herr",
      "lemma": "Herr",
      "pos": "NN",
      "morph": "nom|sg|masc",
      "mother": "22595",
      "rel": "--"
    },
    {
      "index": "22597",
      "text": "Kommissar",
      "lemma": "Kommissar",
      "pos": "NN",
      "morph": "nom|sg|masc",
      "mother": "22596",
      "rel": "NK"
    },
    {
      "index": "22598",
      "text": ",",
      "lemma": "--",
      "pos": "$,",
      "morph": "_",
      "mother": "22597",
      "rel": "--"
    },
    {
      "index": "22599",
      "text": "ich",
      "lemma": "ich",
      "pos": "PPER",
      "morph": "nom|sg|*|1",
      "mother": "22600",
      "rel": "SB"
    },
    {
      "index": "22600",
      "text": "kann",
      "lemma": "k\u00f6nnen",
      "pos": "VMFIN",
      "morph": "sg|3|pres|ind",
      "mother": "22595",
      "rel": "--"
    },
    {
      "index": "22601",
      "text": "nur",
      "lemma": "nur",
      "pos": "ADV",
      "morph": "_",
      "mother": "22600",
      "rel": "MO"
    },
    {
      "index": "22602",
      "text": "zu",
      "lemma": "zu",
      "pos": "APPR",
      "morph": "_",
      "mother": "22605",
      "rel": "MO"
    },
    {
      "index": "22603",
      "text": "dem",
      "lemma": "der",
      "pos": "ART",
      "morph": "dat|sg|masc",
      "mother": "22604",
      "rel": "NK"
    },
    {
      "index": "22604",
      "text": "Schlu\u00df",
      "lemma": "Schlu\u00df",
      "pos": "NN",
      "morph": "dat|sg|masc",
      "mother": "22602",
      "rel": "NK"
    },
    {
      "index": "22605",
      "text": "kommen",
      "lemma": "kommen",
      "pos": "VVINF",
      "morph": "_",
      "mother": "22600",
      "rel": "OC"
    },
    {
      "index": "22606",
      "text": ",",
      "lemma": "--",
      "pos": "$,",
      "morph": "_",
      "mother": "22605",
      "rel": "--"
    },
    {
      "index": "22607",
      "text": "da\u00df",
      "lemma": "da\u00df",
      "pos": "KOUS",
      "morph": "_",
      "mother": "22616",
      "rel": "CP"
    },
    {
      "index": "22608",
      "text": "diese",
      "lemma": "dieser",
      "pos": "PDAT",
      "morph": "nom|sg|fem",
      "mother": "22609",
      "rel": "NK"
    },
    {
      "index": "22609",
      "text": "Vertretung",
      "lemma": "Vertretung",
      "pos": "NN",
      "morph": "nom|sg|fem",
      "mother": "22616",
      "rel": "SB"
    },
    {
      "index": "22610",
      "text": "ihre",
      "lemma": "ihr",
      "pos": "PPOSAT",
      "morph": "nom|sg|fem",
      "mother": "22611",
      "rel": "NK"
    },
    {
      "index": "22611",
      "text": "Arbeit",
      "lemma": "Arbeit",
      "pos": "NN",
      "morph": "nom|sg|fem",
      "mother": "22616",
      "rel": "OA"
    },
    {
      "index": "22612",
      "text": "in",
      "lemma": "in",
      "pos": "APPR",
      "morph": "_",
      "mother": "22611",
      "rel": "MNR"
    },
    {
      "index": "22613",
      "text": "Gro\u00dfbritannien",
      "lemma": "Gro\u00dfbritannien",
      "pos": "NE",
      "morph": "dat|sg|neut",
      "mother": "22612",
      "rel": "NK"
    },
    {
      "index": "22614",
      "text": "nicht",
      "lemma": "nicht",
      "pos": "PTKNEG",
      "morph": "_",
      "mother": "22615",
      "rel": "NG"
    },
    {
      "index": "22615",
      "text": "korrekt",
      "lemma": "korrekt",
      "pos": "ADJD",
      "morph": "pos",
      "mother": "22616",
      "rel": "MO"
    },
    {
      "index": "22616",
      "text": "ausf\u00fchrt",
      "lemma": "ausf\u00fchren",
      "pos": "VVPP",
      "morph": "_",
      "mother": "22596",
      "rel": "OC"
    },
    {
      "index": "22617",
      "text": ".",
      "lemma": "--",
      "pos": "$.",
      "morph": "_",
      "mother": "22616",
      "rel": "--"
    }
  ],
  "sentences": [
    [
      0,
      35
    ],
    [
      35,
      60
    ],
    [
      60,
      105
    ],
    [
      105,
      155
    ],
    [
      155,
      173
    ],
    [
      173,
      204
    ],
    [
      204,
      226
    ]
  ],
  "anaphors": [
    {
      "id": "markable_2976",
      "shellnoun": "false",
      "align_unit": "set_180",
      "start": 185,
      "end": 186,
      "index": 0
    }
  ],
  "antecedents": [
    {
      "id": "markable_2975",
      "nominal": "false",
      "align_unit": "set_179",
      "start": 135,
      "end": 154,
      "index": 0
    },
    {
      "id": "markable_2974",
      "nominal": "false",
      "align_unit": "set_178",
      "start": 126,
      "end": 134,
      "index": 1
    }
  ],
  "ref_instances": []
}